<?xml version="1.0" encoding="UTF-8"?>
<dataroot xmlns:od="urn:schemas-microsoft-com:officedata" xmlns:xsi="http://www.w3.org/2001/XMLSchema-instance" xsi:noNamespaceSchemaLocation="climates.xsd" export_time="Wed Aug 24 13:36:00 2016" revision="28" export_branch="T:/branches/warhammer/bret/warhammer/binaries.x64" export_user="bob">
<edit_uuid>572fbfde-726f-4259-8893-7e4b8cab0eba</edit_uuid>
<climates record_uuid="{e8717e05-e579-4f9d-936d-315c2d4fb853}" record_timestamp="1442221303075" record_key="brt_chs">
<climate_type>brt_chs</climate_type>
</climates>
<climates record_uuid="{c36c6f94-8f5d-4681-975a-dcfc729af228}" record_timestamp="1434970038397" record_key="brt_moorlands">
<climate_type>brt_moorlands</climate_type>
</climates>
<climates record_uuid="{515a51e0-dd97-4c09-b333-6321044870fd}" record_timestamp="1442221303081" record_key="brt_vmp">
<climate_type>brt_vmp</climate_type>
</climates>
<climates record_uuid="{2c25f45c-9cdd-489b-9107-c0e8c564ad1c}" record_timestamp="1461852217051" record_key="bst">
<climate_type>bst</climate_type>
</climates>
<climates record_uuid="{21dc19b0-b696-4e70-bb1e-cc60459ab16b}" record_timestamp="1467719421442" record_key="bst_paths">
<climate_type>bst_paths</climate_type>
</climates>
<climates record_uuid="{d10f26c0-e283-4db8-95df-ad6aa41d59d7}" record_timestamp="1434970038700" record_key="chs_wastes">
<climate_type>chs_wastes</climate_type>
</climates>
<climates record_uuid="{a1cc2504-5c28-48f9-9f01-8585fc01f637}" record_key="default">
<climate_type>default</climate_type>
</climates>
<climates record_uuid="{11efa6bc-ce44-4737-94e6-fa3914dfc75e}" record_timestamp="1434970038496" record_key="dwf_subterranean">
<climate_type>dwf_subterranean</climate_type>
</climates>
<climates record_uuid="{7734c496-474e-4c9d-8dfc-cc2c2e00ae97}" record_timestamp="1442221303072" record_key="emp_chs">
<climate_type>emp_chs</climate_type>
</climates>
<climates record_uuid="{cdb98526-cd35-474e-9358-7da856798df1}" record_timestamp="1434970038918" record_key="emp_highlands">
<climate_type>emp_highlands</climate_type>
</climates>
<climates record_uuid="{ac2216c7-f831-4b32-a1ec-84720c36146c}" record_timestamp="1434970038330" record_key="emp_lowlands">
<climate_type>emp_lowlands</climate_type>
</climates>
<climates record_uuid="{de376115-4848-42d0-b02f-5189001e438e}" record_timestamp="1442221303078" record_key="emp_vmp">
<climate_type>emp_vmp</climate_type>
</climates>
<climates record_uuid="{de0e6c6e-05a1-433a-b194-1aa0850710cd}" record_timestamp="1434970038637" record_key="grn_badlands">
<climate_type>grn_badlands</climate_type>
</climates>
<climates record_uuid="{fbcccedf-a7ed-403b-91fa-56576f8d1130}" record_timestamp="1460466697029" record_key="grn_chs">
<climate_type>grn_chs</climate_type>
</climates>
<climates record_uuid="{c00cf10e-4054-4761-8cac-206d6e30da95}" record_timestamp="1434970038840" record_key="mtn_pass">
<climate_type>mtn_pass</climate_type>
</climates>
<climates record_uuid="{c164f9ca-f22c-4bd6-acbc-f494e61346a4}" record_timestamp="1459951253404" record_key="mtn_pass_snow">
<climate_type>mtn_pass_snow</climate_type>
</climates>
<climates record_uuid="{529a4815-0d99-4d96-b12f-db5d13acbff2}" record_timestamp="1434970038877" record_key="nor_highlands">
<climate_type>nor_highlands</climate_type>
</climates>
<climates record_uuid="{1ae70f00-ac09-4cbe-b734-5eff7a5a918a}" record_timestamp="1434970038563" record_key="nor_lowlands">
<climate_type>nor_lowlands</climate_type>
</climates>
<climates record_uuid="{d7485247-4e61-46d9-8896-fee5fe2aea5f}" record_timestamp="1434970038764" record_key="vmp_marshlands">
<climate_type>vmp_marshlands</climate_type>
</climates>
<climates record_uuid="{8c8c8920-96cc-47bc-9853-e36950367527}" record_timestamp="1467715193826" record_key="wef">
<climate_type>wef</climate_type>
</climates>
<climates record_uuid="{e6edd548-c134-40f1-a707-6b048f05c133}" record_timestamp="1472042160814" record_key="wef_ash">
<climate_type>wef_ash</climate_type>
</climates>
<climates record_uuid="{bed3654f-fa45-4f8a-80d7-06e56742e884}" record_timestamp="1472042160821" record_key="wef_chs">
<climate_type>wef_chs</climate_type>
</climates>
<climates record_uuid="{9eb6b1c8-8604-42bf-b08f-7bf5909b5222}" record_timestamp="1472042160827" record_key="wef_nit">
<climate_type>wef_nit</climate_type>
</climates>
<climates record_uuid="{5541b1a5-fc05-4ccb-b1fc-1a3aa3c197d7}" record_timestamp="1472042160834" record_key="wef_win">
<climate_type>wef_win</climate_type>
</climates>
</dataroot>
