<?xml version="1.0" encoding="UTF-8"?>
<dataroot xmlns:od="urn:schemas-microsoft-com:officedata" xmlns:xsi="http://www.w3.org/2001/XMLSchema-instance" xsi:noNamespaceSchemaLocation="quotes_people.xsd" export_time="Wed Feb 1 12:20:15 2017" revision="39" export_branch="T:/branches/warhammer/bret/warhammer/binaries.x64" export_user="bob">
<edit_uuid>a759533f-0549-4e38-b3c2-907dd5ba9376</edit_uuid>
<quotes_people record_uuid="{83de0805-7a20-49e5-8767-d6eb7c98d7ed}" record_timestamp="1441795575357" record_key="alaric">
<quote_person_key>alaric</quote_person_key>
<quote_person_onscreen state="APPROVED" last_approved_text="Alaric, High Theogonist of Sigmar" last_edit_user="bob">Alaric, High Theogonist of Sigmar</quote_person_onscreen>
</quotes_people>
<quotes_people record_uuid="{0dbe799d-5b55-4ea7-b792-6e4fd61cbae9}" record_timestamp="1484910184358" record_key="albert_du_maurier">
<quote_person_key>albert_du_maurier</quote_person_key>
<quote_person_onscreen state="APPROVED" last_approved_text="Albert du Maurier, Chief Farrier to the Carcasonne Stables" last_edit_user="bob">Albert du Maurier, Chief Farrier to the Carcasonne Stables</quote_person_onscreen>
</quotes_people>
<quotes_people record_uuid="{28578c80-360f-44bd-8171-4e1911cc006c}" record_timestamp="1441715708332" record_key="albrecht_heinz">
<quote_person_key>albrecht_heinz</quote_person_key>
<quote_person_onscreen state="APPROVED" last_approved_text="Albrecht Heinz, Drakwald Militia" last_edit_user="bob">Albrecht Heinz, Drakwald Militia</quote_person_onscreen>
</quotes_people>
<quotes_people record_uuid="{585106e0-022b-4918-ac9f-4463440bca5a}" record_timestamp="1441795575310" record_key="albrecht_of_nuln">
<quote_person_key>albrecht_of_nuln</quote_person_key>
<quote_person_onscreen state="APPROVED" last_approved_text="Albrecht of Nuln" last_edit_user="bob">Albrecht of Nuln</quote_person_onscreen>
</quotes_people>
<quotes_people record_uuid="{c0633d7f-8c5d-43fe-a5eb-b7ae4cc6da13}" record_timestamp="1441715369719" record_key="albrecht_valdorf">
<quote_person_key>albrecht_valdorf</quote_person_key>
<quote_person_onscreen state="APPROVED" last_approved_text="Sir Albrecht Valdorf, Preceptor of the Righteous Lance" last_edit_user="bob">Sir Albrecht Valdorf, Preceptor of the Righteous Lance</quote_person_onscreen>
</quotes_people>
<quotes_people record_uuid="{8ae4c78c-71cb-429b-9040-94f20f6d8a87}" record_timestamp="1441795575139" record_key="alexei_zucharov">
<quote_person_key>alexei_zucharov</quote_person_key>
<quote_person_onscreen state="APPROVED" last_approved_text="Alexei Zucharov, Star of Erengrad" last_edit_user="bob">Alexei Zucharov, Star of Erengrad</quote_person_onscreen>
</quotes_people>
<quotes_people record_uuid="{1c778e6f-f3e5-4f4d-998d-5a23fbaf5430}" record_timestamp="1465373038681" record_key="andreas_halldenstadt">
<quote_person_key>andreas_halldenstadt</quote_person_key>
<quote_person_onscreen state="APPROVED" last_approved_text="Andreas Halldenstadt, Head Scribe at the Great Library of Altdorf" last_edit_user="bob">Andreas Halldenstadt, Head Scribe at the Great Library of Altdorf</quote_person_onscreen>
</quotes_people>
<quotes_people record_uuid="{6606faf9-533c-43e6-926d-0661f570735d}" record_timestamp="1465373038682" record_key="anon">
<quote_person_key>anon</quote_person_key>
<quote_person_onscreen state="APPROVED" last_approved_text="Anonymous" last_edit_user="bob">Anonymous</quote_person_onscreen>
</quotes_people>
<quotes_people record_uuid="{1b24767a-dcbd-4e94-8c6f-c41e899aa36e}" record_timestamp="1441795574905" record_key="arbaal_the_undefeated">
<quote_person_key>arbaal_the_undefeated</quote_person_key>
<quote_person_onscreen state="APPROVED" last_approved_text="Arbaal the Undefeated, at the Siege of Praag" last_edit_user="bob">Arbaal the Undefeated, at the Siege of Praag</quote_person_onscreen>
</quotes_people>
<quotes_people record_uuid="{e30c8062-090e-477a-8370-b2daab64304d}" record_timestamp="1441716313946" record_key="archaon">
<quote_person_key>archaon</quote_person_key>
<quote_person_onscreen state="APPROVED" last_approved_text="Archaon, Lord of the End Times" last_edit_user="bob">Archaon, Lord of the End Times</quote_person_onscreen>
</quotes_people>
<quotes_people record_uuid="{447a7dd4-2e24-472b-bfda-ae3de9605e46}" record_timestamp="1441715959376" record_key="asteron">
<quote_person_key>asteron</quote_person_key>
<quote_person_onscreen state="APPROVED" last_approved_text="Asteron, long-dead monarch of the Dolgars" last_edit_user="bob">Asteron, long-dead monarch of the Dolgars</quote_person_onscreen>
</quotes_people>
<quotes_people record_uuid="{6afc2f5d-a311-4e9d-b3ed-e87edbfae1d5}" record_timestamp="1471865183134" record_key="belegar_assault">
<quote_person_key>belegar_assault</quote_person_key>
<quote_person_onscreen state="APPROVED" last_approved_text="Belegar Ironhammer, King of Karak Eight Peaks, shortly before the main assault" last_edit_user="bob">Belegar Ironhammer, King of Karak Eight Peaks, shortly before the main assault</quote_person_onscreen>
</quotes_people>
<quotes_people record_uuid="{548e4a8e-b932-4a74-a6a1-8f4af8c61769}" record_timestamp="1471865183135" record_key="belegar_ironhammer">
<quote_person_key>belegar_ironhammer</quote_person_key>
<quote_person_onscreen state="APPROVED" last_approved_text="Belegar Ironhammer, King of Karak Eight Peaks" last_edit_user="bob">Belegar Ironhammer, King of Karak Eight Peaks</quote_person_onscreen>
</quotes_people>
<quotes_people record_uuid="{d9b956e7-0900-4493-ab27-4a03ed8e6d8c}" record_timestamp="1471865183134" record_key="belegar_preparing">
<quote_person_key>belegar_preparing</quote_person_key>
<quote_person_onscreen state="APPROVED" last_approved_text="Belegar Ironhammer, King of Karak Eight Peaks, preparing his brave Dawi for the struggle to come" last_edit_user="bob">Belegar Ironhammer, King of Karak Eight Peaks, preparing his brave Dawi for the struggle to come</quote_person_onscreen>
</quotes_people>
<quotes_people record_uuid="{dee17698-ab95-49d9-9934-1b1d680ef09a}" record_timestamp="1465373038683" record_key="bestiarie">
<quote_person_key>bestiarie</quote_person_key>
<quote_person_onscreen state="APPROVED" last_approved_text="Bestiarie Malificent" last_edit_user="bob">Bestiarie Malificent</quote_person_onscreen>
</quotes_people>
<quotes_people record_uuid="{fa97eb03-09e8-4bff-952f-8cb3a0116d0b}" record_timestamp="1465373038682" record_key="bhorgos">
<quote_person_key>bhorgos</quote_person_key>
<quote_person_onscreen state="APPROVED" last_approved_text="Bhorgos Gorehorn, Doombull" last_edit_user="bob">Bhorgos Gorehorn, Doombull</quote_person_onscreen>
</quotes_people>
<quotes_people record_uuid="{fa9bea8f-313b-471e-9486-c437020e7a2b}" record_timestamp="1441716062619" record_key="black_ruyrecht">
<quote_person_key>black_ruyrecht</quote_person_key>
<quote_person_onscreen state="APPROVED" last_approved_text="Black Ruyrecht, veteran of the Vampire Wars" last_edit_user="bob">Black Ruyrecht, veteran of the Vampire Wars</quote_person_onscreen>
</quotes_people>
<quotes_people record_uuid="{c3174ec1-0887-4ce9-89ab-14ceac7d4ea6}" record_timestamp="1441795575248" record_key="boris_kraus_of_nuln">
<quote_person_key>boris_kraus_of_nuln</quote_person_key>
<quote_person_onscreen state="APPROVED" last_approved_text="Boris Kraus of Nuln, Chief Engineer" last_edit_user="bob">Boris Kraus of Nuln, Chief Engineer</quote_person_onscreen>
</quotes_people>
<quotes_people record_uuid="{3d17f422-d24d-4de8-b05b-a90ef62f3dbd}" record_timestamp="1481897367136" record_key="branchclimber">
<quote_person_key>branchclimber</quote_person_key>
<quote_person_onscreen state="APPROVED" last_approved_text="Minaith Branchclimber of the Deepwood Scouts" last_edit_user="bob">Minaith Branchclimber of the Deepwood Scouts</quote_person_onscreen>
</quotes_people>
<quotes_people record_uuid="{d783ca55-b4d2-476e-a8ff-0f8f989c3bc3}" record_timestamp="1441795575482" record_key="captain_helmur_van_hal">
<quote_person_key>captain_helmur_van_hal</quote_person_key>
<quote_person_onscreen state="APPROVED" last_approved_text="Captain Helmur van Hal, Witch Hunter" last_edit_user="bob">Captain Helmur van Hal, Witch Hunter</quote_person_onscreen>
</quotes_people>
<quotes_people record_uuid="{bdab6eee-1897-4a6f-8cb9-edca36fe0682}" record_timestamp="1484910184398" record_key="celeste_verite_damsel">
<quote_person_key>celeste_verite_damsel</quote_person_key>
<quote_person_onscreen state="APPROVED" last_approved_text="Celeste Vérité, Damsel of the Lady" last_edit_user="bob">Celeste Vérité, Damsel of the Lady</quote_person_onscreen>
</quotes_people>
<quotes_people record_uuid="{a142728c-e3c6-48a1-9778-168aa4054a60}" record_timestamp="1477038106570" record_key="charoi">
<quote_person_key>charoi</quote_person_key>
<quote_person_onscreen state="APPROVED" last_approved_text="Charoi Everwatcher, Chief Wildwood Ranger" last_edit_user="bob">Charoi Everwatcher, Chief Wildwood Ranger</quote_person_onscreen>
</quotes_people>
<quotes_people record_uuid="{0047d42b-6151-4f46-9414-b8117eeab117}" record_timestamp="1465373038681" record_key="christof_gamboldini">
<quote_person_key>christof_gamboldini</quote_person_key>
<quote_person_onscreen state="APPROVED" last_approved_text="Christof Gamboldini, Official Chronicler of the Vespero's Vendetta Free Company of Tilea" last_edit_user="bob">Christof Gamboldini, Official Chronicler of the Vespero's Vendetta Free Company of Tilea</quote_person_onscreen>
</quotes_people>
<quotes_people record_uuid="{22a628aa-5b96-44a4-972f-36ea20652f29}" record_timestamp="1441714226175" record_key="clan_ullek">
<quote_person_key>clan_ullek</quote_person_key>
<quote_person_onscreen state="APPROVED" last_approved_text="War cry of Clan Ullek" last_edit_user="bob">War cry of Clan Ullek</quote_person_onscreen>
</quotes_people>
<quotes_people record_uuid="{e7480463-1e1a-4458-8df8-2e2ad216e010}" record_timestamp="1477038106565" record_key="corbeau">
<quote_person_key>corbeau</quote_person_key>
<quote_person_onscreen state="APPROVED" last_approved_text="Henri Corbeau, Bretonnian Soldier" last_edit_user="bob">Henri Corbeau, Bretonnian Soldier</quote_person_onscreen>
</quotes_people>
<quotes_people record_uuid="{370dcef8-4969-4569-8e9e-c4ab335e4f0b}" record_timestamp="1470146854359" record_key="danric_hattsvainn">
<quote_person_key>danric_hattsvainn</quote_person_key>
<quote_person_onscreen state="APPROVED" last_approved_text="Danric Hattsvainn, Keeper of the Holy Texts of the Cult of Ulric" last_edit_user="bob">Danric Hattsvainn, Keeper of the Holy Texts of the Cult of Ulric</quote_person_onscreen>
</quotes_people>
<quotes_people record_uuid="{4d610ea2-0bfd-45cd-84f6-08817d24d7aa}" record_timestamp="1484910184375" record_key="darthon_ironbeard">
<quote_person_key>darthon_ironbeard</quote_person_key>
<quote_person_onscreen state="APPROVED" last_approved_text="Darthon Ironbeard, Dwarflord of the Grey Mountains " last_edit_user="bob">Darthon Ironbeard, Dwarflord of the Grey Mountains </quote_person_onscreen>
</quotes_people>
<quotes_people record_uuid="{d15694ad-c2ac-4227-885b-ea87c75a55be}" record_timestamp="1441714226222" record_key="deadeye_drock">
<quote_person_key>deadeye_drock</quote_person_key>
<quote_person_onscreen state="APPROVED" last_approved_text="Deadeye Drock, Master Gunner" last_edit_user="bob">Deadeye Drock, Master Gunner</quote_person_onscreen>
</quotes_people>
<quotes_people record_uuid="{b610fa2b-b3b0-46b0-9db2-1b475b34209f}" record_timestamp="1470146853736" record_key="dietrich_mirtis">
<quote_person_key>dietrich_mirtis</quote_person_key>
<quote_person_onscreen state="APPROVED" last_approved_text="Dietrich Mirtis, Vampire Count of Vlad's Coven" last_edit_user="bob">Dietrich Mirtis, Vampire Count of Vlad's Coven</quote_person_onscreen>
</quotes_people>
<quotes_people record_uuid="{79b4a337-32d6-4fd6-9efe-e5d526190ed8}" record_timestamp="1441714535884" record_key="durek_hewstone">
<quote_person_key>durek_hewstone</quote_person_key>
<quote_person_onscreen state="APPROVED" last_approved_text="Durek Hewstone, Head Prospector, Karaz-a-Karak" last_edit_user="bob">Durek Hewstone, Head Prospector, Karaz-a-Karak</quote_person_onscreen>
</quotes_people>
<quotes_people record_uuid="{ac849879-0246-41e5-a071-bd7606a53a85}" record_timestamp="1441795574733" record_key="durgrim_redman">
<quote_person_key>durgrim_redman</quote_person_key>
<quote_person_onscreen state="APPROVED" last_approved_text="Durgrim Redman, Dwarf Hammerer" last_edit_user="bob">Durgrim Redman, Dwarf Hammerer</quote_person_onscreen>
</quotes_people>
<quotes_people record_uuid="{97a9205a-62eb-4314-8604-28e0ee0d5a55}" record_timestamp="1441117776942" record_key="dwarf_engineer">
<quote_person_key>dwarf_engineer</quote_person_key>
<quote_person_onscreen state="APPROVED" last_approved_text="Advice from a Dwarf Master Engineer to an apprentice." last_edit_user="bob">Advice from a Dwarf Master Engineer to an apprentice.</quote_person_onscreen>
</quotes_people>
<quotes_people record_uuid="{382e351d-2fba-4a23-9ad3-6e76d4c03587}" record_timestamp="1441795575872" record_key="dwarf_proverb">
<quote_person_key>dwarf_proverb</quote_person_key>
<quote_person_onscreen state="APPROVED" last_approved_text="Dwarf proverb" last_edit_user="bob">Dwarf proverb</quote_person_onscreen>
</quotes_people>
<quotes_people record_uuid="{26ef0795-8ede-4ee5-9a38-2bb684044454}" record_timestamp="1441795574795" record_key="dwarfen_saying">
<quote_person_key>dwarfen_saying</quote_person_key>
<quote_person_onscreen state="APPROVED" last_approved_text="Dwarfen saying" last_edit_user="bob">Dwarfen saying</quote_person_onscreen>
</quotes_people>
<quotes_people record_uuid="{8467c31b-d5b3-4cdf-8e29-5eaf84602b89}" record_timestamp="1470146857042" record_key="eckhart_blitz">
<quote_person_key>eckhart_blitz</quote_person_key>
<quote_person_onscreen state="APPROVED" last_approved_text="Eckhart Blitz, Captain, Ostermark Garrison" last_edit_user="bob">Eckhart Blitz, Captain, Ostermark Garrison</quote_person_onscreen>
</quotes_people>
<quotes_people record_uuid="{6c1da41f-90b6-4360-9e67-9dd579d1eec6}" record_timestamp="1441715152940" record_key="edwalst">
<quote_person_key>edwalst</quote_person_key>
<quote_person_onscreen state="APPROVED" last_approved_text="Captain Edwalst von Hilde" last_edit_user="bob">Captain Edwalst von Hilde</quote_person_onscreen>
</quotes_people>
<quotes_people record_uuid="{4f42f42f-e184-4a43-a290-8461f75ad804}" record_timestamp="1441716526692" record_key="eglixus">
<quote_person_key>eglixus</quote_person_key>
<quote_person_onscreen state="APPROVED" last_approved_text="Eglixus, The Executioner of Trechagrad" last_edit_user="bob">Eglixus, The Executioner of Trechagrad</quote_person_onscreen>
</quotes_people>
<quotes_people record_uuid="{817375ef-3c28-4c0e-8ef8-e8f9f072a507}" record_timestamp="1465373038683" record_key="eisner">
<quote_person_key>eisner</quote_person_key>
<quote_person_onscreen state="APPROVED" last_approved_text="The Trial of Helmut Eisner" last_edit_user="bob">The Trial of Helmut Eisner</quote_person_onscreen>
</quotes_people>
<quotes_people record_uuid="{828d9fbe-011c-4af2-bca4-365509e95afd}" record_timestamp="1470146854515" record_key="empire_soldiers_song">
<quote_person_key>empire_soldiers_song</quote_person_key>
<quote_person_onscreen state="APPROVED" last_approved_text="Empire Soldiers' Song" last_edit_user="bob">Empire Soldiers' Song</quote_person_onscreen>
</quotes_people>
<quotes_people record_uuid="{a84b6281-be1e-4480-8c55-bd66f33d051e}" record_timestamp="1470146853579" record_key="essen_ford_survivor">
<quote_person_key>essen_ford_survivor</quote_person_key>
<quote_person_onscreen state="APPROVED" last_approved_text="Survivor of the Battle of Essen Ford (Nameless)" last_edit_user="bob">Survivor of the Battle of Essen Ford (Nameless)</quote_person_onscreen>
</quotes_people>
<quotes_people record_uuid="{5a583312-5d7c-47c0-a12f-5f1b5e070ec4}" record_timestamp="1477038106571" record_key="ethalin">
<quote_person_key>ethalin</quote_person_key>
<quote_person_onscreen state="APPROVED" last_approved_text="Lord Ethalin of the Pine Crags" last_edit_user="bob">Lord Ethalin of the Pine Crags</quote_person_onscreen>
</quotes_people>
<quotes_people record_uuid="{0dd2779f-a9fe-4066-9683-87d6b9cbe347}" record_timestamp="1441795576340" record_key="festus_the_leechlord">
<quote_person_key>festus_the_leechlord</quote_person_key>
<quote_person_onscreen state="APPROVED" last_approved_text="Festus the Leechlord" last_edit_user="bob">Festus the Leechlord</quote_person_onscreen>
</quotes_people>
<quotes_people record_uuid="{806c985d-d41f-4bbf-af73-642987618453}" record_timestamp="1477038106568" record_key="fleetfoot">
<quote_person_key>fleetfoot</quote_person_key>
<quote_person_onscreen state="APPROVED" last_approved_text="Lecai Fleetfoot, Deepwood Scout and would-be philosopher" last_edit_user="bob">Lecai Fleetfoot, Deepwood Scout and would-be philosopher</quote_person_onscreen>
</quotes_people>
<quotes_people record_uuid="{5bd2e293-df3d-4b94-b787-55968b68e0df}" record_timestamp="1477038106570" record_key="fontaine">
<quote_person_key>fontaine</quote_person_key>
<quote_person_onscreen state="APPROVED" last_approved_text="Marc de la Fontaine, Bretonnian historian and Wood Elf expert" last_edit_user="bob">Marc de la Fontaine, Bretonnian historian and Wood Elf expert</quote_person_onscreen>
</quotes_people>
<quotes_people record_uuid="{6b305bed-1325-4a56-97d6-8d58a46d04ab}" record_timestamp="1441795576246" record_key="fregnus_the_pallid">
<quote_person_key>fregnus_the_pallid</quote_person_key>
<quote_person_onscreen state="APPROVED" last_approved_text="Fregnus the Pallid" last_edit_user="bob">Fregnus the Pallid</quote_person_onscreen>
</quotes_people>
<quotes_people record_uuid="{1488835a-678e-4519-a727-a90618520d1d}" record_timestamp="1441795576090" record_key="gabber">
<quote_person_key>gabber</quote_person_key>
<quote_person_onscreen state="APPROVED" last_approved_text="Gabber, Orc" last_edit_user="bob">Gabber, Orc</quote_person_onscreen>
</quotes_people>
<quotes_people record_uuid="{23b55239-efd6-411d-8510-d26d77c6af20}" record_timestamp="1441795575919" record_key="gialar_kunst">
<quote_person_key>gialar_kunst</quote_person_key>
<quote_person_onscreen state="APPROVED" last_approved_text="Gialar Kunst, Dwarf Loremaster" last_edit_user="bob">Gialar Kunst, Dwarf Loremaster</quote_person_onscreen>
</quotes_people>
<quotes_people record_uuid="{94225bc3-3e72-4e37-9c56-80969509c68f}" record_timestamp="1441116438994" record_key="gitilla">
<quote_person_key>gitilla</quote_person_key>
<quote_person_onscreen state="APPROVED" last_approved_text="Gitilla da Hunter, Goblin Wolf Rider raider boss" last_edit_user="bob">Gitilla da Hunter, Goblin Wolf Rider raider boss</quote_person_onscreen>
</quotes_people>
<quotes_people record_uuid="{7a514b71-5dca-42dd-9e0a-b12d50f4657e}" record_timestamp="1441795574546" record_key="gorduz_backstabber">
<quote_person_key>gorduz_backstabber</quote_person_key>
<quote_person_onscreen state="APPROVED" last_approved_text="Gorduz Backstabber" last_edit_user="bob">Gorduz Backstabber</quote_person_onscreen>
</quotes_people>
<quotes_people record_uuid="{2a5d5730-5b44-48eb-a5da-6883230ac03f}" record_timestamp="1441713443255" record_key="grail_vow">
<quote_person_key>grail_vow</quote_person_key>
<quote_person_onscreen state="APPROVED" last_approved_text="The Grail Vow" last_edit_user="bob">The Grail Vow</quote_person_onscreen>
</quotes_people>
<quotes_people record_uuid="{fe7e295e-4b13-41bc-b8a2-6856f4d04823}" record_timestamp="1441116439238" record_key="greebitz">
<quote_person_key>greebitz</quote_person_key>
<quote_person_onscreen state="APPROVED" last_approved_text="Greebitz, Goblin lackey of Warboss Ugg" last_edit_user="bob">Greebitz, Goblin lackey of Warboss Ugg</quote_person_onscreen>
</quotes_people>
<quotes_people record_uuid="{f39a259b-f069-4469-b66b-4ce0227a1cb0}" record_timestamp="1485951311096" record_key="gregoire">
<quote_person_key>gregoire</quote_person_key>
<quote_person_onscreen state="APPROVED" last_approved_text="Grégoire du Haut Chateau, Nobleman, Peasant-Hater" last_edit_user="bob">Grégoire du Haut Chateau, Nobleman, Peasant-Hater</quote_person_onscreen>
</quotes_people>
<quotes_people record_uuid="{4b84bd48-6bcf-4553-b2f1-221b2be6cea7}" record_timestamp="1449248737928" record_key="grimgor">
<quote_person_key>grimgor</quote_person_key>
<quote_person_onscreen state="APPROVED" last_approved_text="Grimgor Ironhide, Black Orc Warboss" last_edit_user="bob">Grimgor Ironhide, Black Orc Warboss</quote_person_onscreen>
</quotes_people>
<quotes_people record_uuid="{f9290212-51df-4d5f-bd36-d5b1e0fff1cf}" record_timestamp="1441116439076" record_key="grizgutz">
<quote_person_key>grizgutz</quote_person_key>
<quote_person_onscreen state="APPROVED" last_approved_text="Grizgutz Badax, Orc Warlord" last_edit_user="bob">Grizgutz Badax, Orc Warlord</quote_person_onscreen>
</quotes_people>
<quotes_people record_uuid="{bafa36b8-fe04-4797-907a-83558598c458}" record_timestamp="1441795576449" record_key="gunthar_klaus">
<quote_person_key>gunthar_klaus</quote_person_key>
<quote_person_onscreen state="APPROVED" last_approved_text="Warrior Priest Gunthar Klaus" last_edit_user="bob">Warrior Priest Gunthar Klaus</quote_person_onscreen>
</quotes_people>
<quotes_people record_uuid="{d809458c-a2a8-48af-92b9-aa297544187c}" record_timestamp="1471865183135" record_key="gurnisson_glorious">
<quote_person_key>gurnisson_glorious</quote_person_key>
<quote_person_onscreen state="APPROVED" last_approved_text="Gotrek Gurnisson, former inhabitant of Karak Eight Peaks, speaking of its glorious aspect" last_edit_user="bob">Gotrek Gurnisson, former inhabitant of Karak Eight Peaks, speaking of its glorious aspect</quote_person_onscreen>
</quotes_people>
<quotes_people record_uuid="{c840ac48-7414-4e46-9bca-515ba4c2d70a}" record_timestamp="1471865183134" record_key="gurnisson_inhabitant">
<quote_person_key>gurnisson_inhabitant</quote_person_key>
<quote_person_onscreen state="APPROVED" last_approved_text="Gotrek Gurnisson, former inhabitant of Karak Eight Peaks" last_edit_user="bob">Gotrek Gurnisson, former inhabitant of Karak Eight Peaks</quote_person_onscreen>
</quotes_people>
<quotes_people record_uuid="{30b6ddfe-a38a-4670-9099-5722790287d5}" record_timestamp="1441716218983" record_key="ingeheim">
<quote_person_key>ingeheim</quote_person_key>
<quote_person_onscreen state="APPROVED" last_approved_text="Witch Hunter von Ingeheim" last_edit_user="bob">Witch Hunter von Ingeheim</quote_person_onscreen>
</quotes_people>
<quotes_people record_uuid="{c9640531-77c9-4111-b9db-0deaeebdc031}" record_timestamp="1441716104934" record_key="isabella">
<quote_person_key>isabella</quote_person_key>
<quote_person_onscreen state="APPROVED" last_approved_text="Isabella von Carstein" last_edit_user="bob">Isabella von Carstein</quote_person_onscreen>
</quotes_people>
<quotes_people record_uuid="{c95b4f6e-09a6-4788-9bfd-fa8f12b1111f}" record_timestamp="1441795575981" record_key="isabella_von_carstein">
<quote_person_key>isabella_von_carstein</quote_person_key>
<quote_person_onscreen state="APPROVED" last_approved_text="Isabella von Carstein" last_edit_user="bob">Isabella von Carstein</quote_person_onscreen>
</quotes_people>
<quotes_people record_uuid="{2626daea-0751-41b0-8015-d8d498ccc8a2}" record_timestamp="1470146854204" record_key="ivan_steinmann">
<quote_person_key>ivan_steinmann</quote_person_key>
<quote_person_onscreen state="APPROVED" last_approved_text="Ivan Steinmann, Quartermaster, Middenland Garrison" last_edit_user="bob">Ivan Steinmann, Quartermaster, Middenland Garrison</quote_person_onscreen>
</quotes_people>
<quotes_people record_uuid="{6a408464-f614-4d2e-a3db-e76f6466548f}" record_timestamp="1484910184347" record_key="jason_le_wallier">
<quote_person_key>jason_le_wallier</quote_person_key>
<quote_person_onscreen state="APPROVED" last_approved_text="Jason le Wallier, Chief Gestour to King Louen Leoncoeur" last_edit_user="bob">Jason le Wallier, Chief Gestour to King Louen Leoncoeur</quote_person_onscreen>
</quotes_people>
<quotes_people record_uuid="{7f2a2d39-6f4b-4ef5-a93d-3c03df4fb0ae}" record_timestamp="1441116438830" record_key="karak_azul">
<quote_person_key>karak_azul</quote_person_key>
<quote_person_onscreen state="APPROVED" last_approved_text="The Karak Azul Book of Grudges" last_edit_user="bob">The Karak Azul Book of Grudges</quote_person_onscreen>
</quotes_people>
<quotes_people record_uuid="{5470d19c-e9ef-479d-a090-c038fdbd577c}" record_timestamp="1441795575529" record_key="karl_althaus">
<quote_person_key>karl_althaus</quote_person_key>
<quote_person_onscreen state="APPROVED" last_approved_text="Karl Althaus, Imperial Pikeman " last_edit_user="bob">Karl Althaus, Imperial Pikeman </quote_person_onscreen>
</quotes_people>
<quotes_people record_uuid="{7fced9cc-114f-493a-b064-62d203417a8d}" record_timestamp="1441795575076" record_key="kaspar_von_kelten">
<quote_person_key>kaspar_von_kelten</quote_person_key>
<quote_person_onscreen state="APPROVED" last_approved_text="Kaspar Von Kelten" last_edit_user="bob">Kaspar Von Kelten</quote_person_onscreen>
</quotes_people>
<quotes_people record_uuid="{7e22f841-5d79-4229-8846-9489f6522c92}" record_timestamp="1465373038682" record_key="khargar">
<quote_person_key>khargar</quote_person_key>
<quote_person_onscreen state="APPROVED" last_approved_text="Khargar, of the Tribe of the Blooded Axe" last_edit_user="bob">Khargar, of the Tribe of the Blooded Axe</quote_person_onscreen>
</quotes_people>
<quotes_people record_uuid="{4220f8ec-ef56-4082-ad1e-3b352e44304d}" record_timestamp="1484910184332" record_key="knightly_vow">
<quote_person_key>knightly_vow</quote_person_key>
<quote_person_onscreen state="APPROVED" last_approved_text="The Knight's Vow" last_edit_user="bob">The Knight's Vow</quote_person_onscreen>
</quotes_people>
<quotes_people record_uuid="{106a4622-d8e2-40dc-a00f-333c36a885df}" record_timestamp="1441713443192" record_key="knights_vow">
<quote_person_key>knights_vow</quote_person_key>
<quote_person_onscreen state="APPROVED" last_approved_text="The Knight's Vow" last_edit_user="bob">The Knight's Vow</quote_person_onscreen>
</quotes_people>
<quotes_people record_uuid="{dbd8214e-eb40-45ff-b10f-ab219d2381a4}" record_timestamp="1441795574437" record_key="konrad_von_carstein">
<quote_person_key>konrad_von_carstein</quote_person_key>
<quote_person_onscreen state="APPROVED" last_approved_text="Konrad von Carstein" last_edit_user="bob">Konrad von Carstein</quote_person_onscreen>
</quotes_people>
<quotes_people record_uuid="{3bdcef3b-5e54-4f61-8116-b90ac91b4d2e}" record_timestamp="1441795574374" record_key="konrad_von_carstein_last_words">
<quote_person_key>konrad_von_carstein_last_words</quote_person_key>
<quote_person_onscreen state="APPROVED" last_approved_text="Konrad von Carstein (last words)" last_edit_user="bob">Konrad von Carstein (last words)</quote_person_onscreen>
</quotes_people>
<quotes_people record_uuid="{ef5aa21a-29cb-4204-844f-47df2017948e}" record_timestamp="1441715230347" record_key="kurt_helborg">
<quote_person_key>kurt_helborg</quote_person_key>
<quote_person_onscreen state="APPROVED" last_approved_text="Kurt Helborg, The Reiksmarshal" last_edit_user="bob">Kurt Helborg, The Reiksmarshal</quote_person_onscreen>
</quotes_people>
<quotes_people record_uuid="{f10abc62-84a2-4e61-9453-507eb668b136}" record_timestamp="1484910184369" record_key="lafayette_taureau">
<quote_person_key>lafayette_taureau</quote_person_key>
<quote_person_onscreen state="APPROVED" last_approved_text="Lafayette du Taureau, Commander of the Couronne Garrison." last_edit_user="bob">Lafayette du Taureau, Commander of the Couronne Garrison.</quote_person_onscreen>
</quotes_people>
<quotes_people record_uuid="{356628cc-2b7b-47c9-8508-fdd4589e9871}" record_timestamp="1484910184351" record_key="lancelot_pondrecoq">
<quote_person_key>lancelot_pondrecoq</quote_person_key>
<quote_person_onscreen state="APPROVED" last_approved_text="Lancelot Pondrecoq, Questing Knight" last_edit_user="bob">Lancelot Pondrecoq, Questing Knight</quote_person_onscreen>
</quotes_people>
<quotes_people record_uuid="{5d871583-808e-45c3-9fb0-16cf0092d158}" record_timestamp="1441795576184" record_key="liber_malefic">
<quote_person_key>liber_malefic</quote_person_key>
<quote_person_onscreen state="APPROVED" last_approved_text="Liber Malefic, concerning Horrors of Tzeentch" last_edit_user="bob">Liber Malefic, concerning Horrors of Tzeentch</quote_person_onscreen>
</quotes_people>
<quotes_people record_uuid="{c2d0efbf-abe5-43a7-b3ee-6bd1bee23655}" record_timestamp="1484910184392" record_key="louen_king">
<quote_person_key>louen_king</quote_person_key>
<quote_person_onscreen state="APPROVED" last_approved_text="Louen Leoncoeur, King of Bretonnia, Grail Knight" last_edit_user="bob">Louen Leoncoeur, King of Bretonnia, Grail Knight</quote_person_onscreen>
</quotes_people>
<quotes_people record_uuid="{0a9ec265-703a-40d4-b487-0faeece6e2c8}" record_timestamp="1471865183135" record_key="magda_freyadotter">
<quote_person_key>magda_freyadotter</quote_person_key>
<quote_person_onscreen state="APPROVED" last_approved_text="Magda Freyadotter, Priestess of Valaya and Counsel of Prince Belegar of Karak Eight Peaks" last_edit_user="bob">Magda Freyadotter, Priestess of Valaya and Counsel of Prince Belegar of Karak Eight Peaks</quote_person_onscreen>
</quotes_people>
<quotes_people record_uuid="{fa823f8f-0e19-4b4b-9ee8-2a739ceec783}" record_timestamp="1441715294025" record_key="magnus">
<quote_person_key>magnus</quote_person_key>
<quote_person_onscreen state="APPROVED" last_approved_text="Magnus the Pious" last_edit_user="bob">Magnus the Pious</quote_person_onscreen>
</quotes_people>
<quotes_people record_uuid="{9d3c7b31-2f72-458f-bfb1-b10434fb8542}" record_timestamp="1465373038682" record_key="malagor">
<quote_person_key>malagor</quote_person_key>
<quote_person_onscreen state="APPROVED" last_approved_text="Malagor, the Dark Omen" last_edit_user="bob">Malagor, the Dark Omen</quote_person_onscreen>
</quotes_people>
<quotes_people record_uuid="{e2f51fef-3723-4465-a745-019326d826ce}" record_timestamp="1465373038682" record_key="malfeasant">
<quote_person_key>malfeasant</quote_person_key>
<quote_person_onscreen state="APPROVED" last_approved_text="The Strange Tale of Doctor Malfeasant" last_edit_user="bob">The Strange Tale of Doctor Malfeasant</quote_person_onscreen>
</quotes_people>
<quotes_people record_uuid="{a78ccaa7-3162-4df2-b6b3-db783f98963c}" record_timestamp="1441795574312" record_key="mannfred_von_carstein">
<quote_person_key>mannfred_von_carstein</quote_person_key>
<quote_person_onscreen state="APPROVED" last_approved_text="Mannfred von Carstein" last_edit_user="bob">Mannfred von Carstein</quote_person_onscreen>
</quotes_people>
<quotes_people record_uuid="{8e359c09-b14f-4b5d-8b54-2fe32e2701b0}" record_timestamp="1484910184363" record_key="marcelle_du_nottin">
<quote_person_key>marcelle_du_nottin</quote_person_key>
<quote_person_onscreen state="APPROVED" last_approved_text="Marcelle du Nottin, Scholar of the Grail" last_edit_user="bob">Marcelle du Nottin, Scholar of the Grail</quote_person_onscreen>
</quotes_people>
<quotes_people record_uuid="{54bf7a98-c147-44d4-a312-8ea5a4c7af41}" record_timestamp="1470146854048" record_key="marius_leitdorf">
<quote_person_key>marius_leitdorf</quote_person_key>
<quote_person_onscreen state="APPROVED" last_approved_text="Marius Leitdorf, Mad Count of Averland" last_edit_user="bob">Marius Leitdorf, Mad Count of Averland</quote_person_onscreen>
</quotes_people>
<quotes_people record_uuid="{2c2a3067-451c-4774-b666-1fba86296e3b}" record_timestamp="1484910184381" record_key="markus_leibniz">
<quote_person_key>markus_leibniz</quote_person_key>
<quote_person_onscreen state="APPROVED" last_approved_text="Markus Leibniz, General of the 4th Wissenland Division" last_edit_user="bob">Markus Leibniz, General of the 4th Wissenland Division</quote_person_onscreen>
</quotes_people>
<quotes_people record_uuid="{3472bafb-2949-49a6-a58d-bc287a5f8b55}" record_timestamp="1441714947105" record_key="markus_wulfhart">
<quote_person_key>markus_wulfhart</quote_person_key>
<quote_person_onscreen state="APPROVED" last_approved_text="Markus Wulfhart, the Huntsmarshal of the Empire" last_edit_user="bob">Markus Wulfhart, the Huntsmarshal of the Empire</quote_person_onscreen>
</quotes_people>
<quotes_people record_uuid="{8e742e64-d3a9-4aab-ab20-4016417fb40b}" record_timestamp="1465373038681" record_key="martin_fortberg">
<quote_person_key>martin_fortberg</quote_person_key>
<quote_person_onscreen state="APPROVED" last_approved_text="Martin Fortberg, Chief Powderjack at the Imperial Gunnery School, Nuln" last_edit_user="bob">Martin Fortberg, Chief Powderjack at the Imperial Gunnery School, Nuln</quote_person_onscreen>
</quotes_people>
<quotes_people record_uuid="{bd5ebe42-70da-476f-9826-9365c7bbbdd0}" record_timestamp="1484910184340" record_key="matthias_von_pfeildorf">
<quote_person_key>matthias_von_pfeildorf</quote_person_key>
<quote_person_onscreen state="APPROVED" last_approved_text="Matthias von Pfeildorf, former Imperial Envoy to Couronne" last_edit_user="bob">Matthias von Pfeildorf, former Imperial Envoy to Couronne</quote_person_onscreen>
</quotes_people>
<quotes_people record_uuid="{d2667262-f5d5-4412-8344-830f1e4cfadc}" record_timestamp="1477038106567" record_key="menlui">
<quote_person_key>menlui</quote_person_key>
<quote_person_onscreen state="APPROVED" last_approved_text="Lady Menlui of the Witherhold" last_edit_user="bob">Lady Menlui of the Witherhold</quote_person_onscreen>
</quotes_people>
<quotes_people record_uuid="{85475cfb-a8d4-46e8-b661-26302bea5e5b}" record_timestamp="1449248737928" record_key="morglum">
<quote_person_key>morglum</quote_person_key>
<quote_person_onscreen state="APPROVED" last_approved_text="Morglum Necksnapper, Orc Warboss" last_edit_user="bob">Morglum Necksnapper, Orc Warboss</quote_person_onscreen>
</quotes_people>
<quotes_people record_uuid="{40cb15e9-a533-44ca-848a-f76cd671faea}" record_timestamp="1441795574608" record_key="morglum_necksnapper">
<quote_person_key>morglum_necksnapper</quote_person_key>
<quote_person_onscreen state="APPROVED" last_approved_text="Morglum Necksnapper" last_edit_user="bob">Morglum Necksnapper</quote_person_onscreen>
</quotes_people>
<quotes_people record_uuid="{2623bc77-80d6-4cd0-b3d9-1fc2fd19a2cb}" record_timestamp="1465373038682" record_key="nowl">
<quote_person_key>nowl</quote_person_key>
<quote_person_onscreen state="APPROVED" last_approved_text="Blind Nowl, the Seer of Parravon" last_edit_user="bob">Blind Nowl, the Seer of Parravon</quote_person_onscreen>
</quotes_people>
<quotes_people record_uuid="{86b16ec2-1acd-47aa-b533-b2f68b721e76}" record_timestamp="1441714593025" record_key="oldor_greybeard">
<quote_person_key>oldor_greybeard</quote_person_key>
<quote_person_onscreen state="APPROVED" last_approved_text="Oldor Greybeard, Prospector" last_edit_user="bob">Oldor Greybeard, Prospector</quote_person_onscreen>
</quotes_people>
<quotes_people record_uuid="{11221871-4cb0-43c7-87d2-58bd680d67c9}" record_timestamp="1465373038682" record_key="onceman">
<quote_person_key>onceman</quote_person_key>
<quote_person_onscreen state="APPROVED" last_approved_text="Heinrich Onceman" last_edit_user="bob">Heinrich Onceman</quote_person_onscreen>
</quotes_people>
<quotes_people record_uuid="{fb54ef87-391d-4d2f-9b61-d6c898802eaa}" record_timestamp="1441116438911" record_key="orc">
<quote_person_key>orc</quote_person_key>
<quote_person_onscreen state="APPROVED" last_approved_text="Orc War Chant" last_edit_user="bob">Orc War Chant</quote_person_onscreen>
</quotes_people>
<quotes_people record_uuid="{a197ff5d-f6cf-4e3d-9286-da5a4c0b0f56}" record_timestamp="1441116439157" record_key="orc_giant_quote">
<quote_person_key>orc_giant_quote</quote_person_key>
<quote_person_onscreen state="APPROVED" last_approved_text="An Orc Big Boss, talking about his tribe's Giant" last_edit_user="bob">An Orc Big Boss, talking about his tribe's Giant</quote_person_onscreen>
</quotes_people>
<quotes_people record_uuid="{5e06cbfd-2d77-45f9-b034-ff3592a168c8}" record_timestamp="1484910184343" record_key="peasant_vows">
<quote_person_key>peasant_vows</quote_person_key>
<quote_person_onscreen state="APPROVED" last_approved_text="Vows of the Peasants unto their Bretonnian Lord" last_edit_user="bob">Vows of the Peasants unto their Bretonnian Lord</quote_person_onscreen>
</quotes_people>
<quotes_people record_uuid="{fa723b32-93dd-4377-9194-c13c92dd9214}" record_timestamp="1441713320792" record_key="peasants_duty">
<quote_person_key>peasants_duty</quote_person_key>
<quote_person_onscreen state="APPROVED" last_approved_text="The Peasant's Duty" last_edit_user="bob">The Peasant's Duty</quote_person_onscreen>
</quotes_people>
<quotes_people record_uuid="{53ffece6-0a6e-438f-9a5f-8bbceed5d7db}" record_timestamp="1465373038681" record_key="petrus_staveheart">
<quote_person_key>petrus_staveheart</quote_person_key>
<quote_person_onscreen state="APPROVED" last_approved_text="Petrus Staveheart, Official Scribe of the Holy Order of the Templars of Sigmar" last_edit_user="bob">Petrus Staveheart, Official Scribe of the Holy Order of the Templars of Sigmar</quote_person_onscreen>
</quotes_people>
<quotes_people record_uuid="{b775f568-5a35-49e1-ad99-adf39d30efd3}" record_timestamp="1441713443239" record_key="questing_vow">
<quote_person_key>questing_vow</quote_person_key>
<quote_person_onscreen state="APPROVED" last_approved_text="The Questing Vow" last_edit_user="bob">The Questing Vow</quote_person_onscreen>
</quotes_people>
<quotes_people record_uuid="{8504cbfa-e810-4b37-a096-980798fb731b}" record_timestamp="1441795576293" record_key="rakranos">
<quote_person_key>rakranos</quote_person_key>
<quote_person_onscreen state="APPROVED" last_approved_text="Rakranos the Ancient, Dragon Ogre Shaggoth" last_edit_user="bob">Rakranos the Ancient, Dragon Ogre Shaggoth</quote_person_onscreen>
</quotes_people>
<quotes_people record_uuid="{70347b19-bc21-489c-a731-c9689efeece0}" record_timestamp="1441795575638" record_key="reiklander_joke">
<quote_person_key>reiklander_joke</quote_person_key>
<quote_person_onscreen state="APPROVED" last_approved_text="Reiklander joke" last_edit_user="bob">Reiklander joke</quote_person_onscreen>
</quotes_people>
<quotes_people record_uuid="{d81a7e7b-fba4-44bb-accc-acabce665597}" record_timestamp="1441795576402" record_key="reiksmarshal_trenkenhoff">
<quote_person_key>reiksmarshal_trenkenhoff</quote_person_key>
<quote_person_onscreen state="APPROVED" last_approved_text="Reiksmarshal Trenkenhoff" last_edit_user="bob">Reiksmarshal Trenkenhoff</quote_person_onscreen>
</quotes_people>
<quotes_people record_uuid="{f5d5f256-a62a-4f60-82db-048698119d5f}" record_timestamp="1465373038682" record_key="reikwald">
<quote_person_key>reikwald</quote_person_key>
<quote_person_onscreen state="APPROVED" last_approved_text="Sole survivor of the Reikwald Forest Patrol" last_edit_user="bob">Sole survivor of the Reikwald Forest Patrol</quote_person_onscreen>
</quotes_people>
<quotes_people record_uuid="{f872efcc-adca-478b-898a-d9d0d8a64cd7}" record_timestamp="1465373038682" record_key="reinhold">
<quote_person_key>reinhold</quote_person_key>
<quote_person_onscreen state="APPROVED" last_approved_text="Arthus Reinhold" last_edit_user="bob">Arthus Reinhold</quote_person_onscreen>
</quotes_people>
<quotes_people record_uuid="{9aa60f12-fdab-420b-94f2-86199e12bb46}" record_timestamp="1441117777022" record_key="rekthor">
<quote_person_key>rekthor</quote_person_key>
<quote_person_onscreen state="APPROVED" last_approved_text="Rekthor Redaxe, Dwarfen Giant Slayer (deceased)" last_edit_user="bob">Rekthor Redaxe, Dwarfen Giant Slayer (deceased)</quote_person_onscreen>
</quotes_people>
<quotes_people record_uuid="{e11280b9-a142-4120-84ab-f9b15b704f02}" record_timestamp="1465373038682" record_key="renkler">
<quote_person_key>renkler</quote_person_key>
<quote_person_onscreen state="APPROVED" last_approved_text="Marcus Renkler, squire and pistolier to the House of Middenheim" last_edit_user="bob">Marcus Renkler, squire and pistolier to the House of Middenheim</quote_person_onscreen>
</quotes_people>
<quotes_people record_uuid="{f84905bd-d257-46c3-b7b3-bf123ea1d648}" record_timestamp="1470146853892" record_key="rineheart_prinzbild">
<quote_person_key>rineheart_prinzbild</quote_person_key>
<quote_person_onscreen state="APPROVED" last_approved_text="Rinehart Prinzbild, Official Portraitist to the Imperial Court" last_edit_user="bob">Rinehart Prinzbild, Official Portraitist to the Imperial Court</quote_person_onscreen>
</quotes_people>
<quotes_people record_uuid="{d0c23a3b-c965-4104-8518-2105e576c75e}" record_timestamp="1465373038682" record_key="rittlehof">
<quote_person_key>rittlehof</quote_person_key>
<quote_person_onscreen state="APPROVED" last_approved_text="Oskar Rittlehof, Veteran Huntsman" last_edit_user="bob">Oskar Rittlehof, Veteran Huntsman</quote_person_onscreen>
</quotes_people>
<quotes_people record_uuid="{aa9c4b87-b7ce-4a25-9f32-326e3ac5d467}" record_timestamp="1484910184335" record_key="ritual_vow">
<quote_person_key>ritual_vow</quote_person_key>
<quote_person_onscreen state="APPROVED" last_approved_text="Ritual vow of a Knight of the Realm" last_edit_user="bob">Ritual vow of a Knight of the Realm</quote_person_onscreen>
</quotes_people>
<quotes_people record_uuid="{f50fd640-d9b6-432f-89b4-30d64b71a9fb}" record_timestamp="1477038106564" record_key="sarathai">
<quote_person_key>sarathai</quote_person_key>
<quote_person_onscreen state="APPROVED" last_approved_text="Sarathai Spiritwalker, Second Spellsinger to the Guard of Isha" last_edit_user="bob">Sarathai Spiritwalker, Second Spellsinger to the Guard of Isha</quote_person_onscreen>
</quotes_people>
<quotes_people record_uuid="{398c9d30-bb2d-49df-bbae-80d09e47b275}" record_timestamp="1465373038682" record_key="schwalz">
<quote_person_key>schwalz</quote_person_key>
<quote_person_onscreen state="APPROVED" last_approved_text="&quot;Mad&quot; Schwalz, the Idiot of Sternburg" last_edit_user="bob">&quot;Mad&quot; Schwalz, the Idiot of Sternburg</quote_person_onscreen>
</quotes_people>
<quotes_people record_uuid="{2dd3cdc2-9806-4e83-9a06-7fc9bd8f92cf}" record_timestamp="1441716648936" record_key="scyla">
<quote_person_key>scyla</quote_person_key>
<quote_person_onscreen state="APPROVED" last_approved_text="Scyla Anfingrimm" last_edit_user="bob">Scyla Anfingrimm</quote_person_onscreen>
</quotes_people>
<quotes_people record_uuid="{8a255e33-940b-4c9a-9f61-9d3529407658}" record_timestamp="1441795576137" record_key="sheglak">
<quote_person_key>sheglak</quote_person_key>
<quote_person_onscreen state="APPROVED" last_approved_text="Sheglak, Orc Shaman" last_edit_user="bob">Sheglak, Orc Shaman</quote_person_onscreen>
</quotes_people>
<quotes_people record_uuid="{96e55c63-0690-4867-ab3b-06b6123afe2a}" record_timestamp="1477038106566" record_key="silverwing">
<quote_person_key>silverwing</quote_person_key>
<quote_person_onscreen state="APPROVED" last_approved_text="Treiya Silverwing, Spellsinger" last_edit_user="bob">Treiya Silverwing, Spellsinger</quote_person_onscreen>
</quotes_people>
<quotes_people record_uuid="{fba40fe7-0e02-47a4-bfb2-aa9b0ba2478e}" record_timestamp="1471865183135" record_key="skarsnik">
<quote_person_key>skarsnik</quote_person_key>
<quote_person_onscreen state="APPROVED" last_approved_text="Skarsnik, Warlord of the Eight Peaks" last_edit_user="bob">Skarsnik, Warlord of the Eight Peaks</quote_person_onscreen>
</quotes_people>
<quotes_people record_uuid="{8eeac38b-e281-4216-aa8a-4adaa6b524bd}" record_timestamp="1471865183135" record_key="skarsnik_bickenstadt">
<quote_person_key>skarsnik_bickenstadt</quote_person_key>
<quote_person_onscreen state="APPROVED" last_approved_text="Skarsnik, as he commands the playwright Bickenstadt to write the story of his life" last_edit_user="bob">Skarsnik, as he commands the playwright Bickenstadt to write the story of his life</quote_person_onscreen>
</quotes_people>
<quotes_people record_uuid="{041a429a-afef-4ce1-a1da-e6ad233176d1}" record_timestamp="1471865183135" record_key="skarsnik_life">
<quote_person_key>skarsnik_life</quote_person_key>
<quote_person_onscreen state="APPROVED" last_approved_text="The Life of Skarsnik" last_edit_user="bob">The Life of Skarsnik</quote_person_onscreen>
</quotes_people>
<quotes_people record_uuid="{13f1b747-7855-4f07-8a70-b7334fe4159c}" record_timestamp="1471865183134" record_key="skarsnik_squig">
<quote_person_key>skarsnik_squig</quote_person_key>
<quote_person_onscreen state="APPROVED" last_approved_text="Skarsnik, talking to his beloved pet Squig" last_edit_user="bob">Skarsnik, talking to his beloved pet Squig</quote_person_onscreen>
</quotes_people>
<quotes_people record_uuid="{e83bd61e-a3f9-4612-ab1c-376e3b12fca5}" record_timestamp="1441795575700" record_key="stirlander_proverb">
<quote_person_key>stirlander_proverb</quote_person_key>
<quote_person_onscreen state="APPROVED" last_approved_text="Stirlander Proverb" last_edit_user="bob">Stirlander Proverb</quote_person_onscreen>
</quotes_people>
<quotes_people record_uuid="{a8250b95-d46e-422d-b977-b0b064acaa89}" record_timestamp="1477038106569" record_key="stonesplitter">
<quote_person_key>stonesplitter</quote_person_key>
<quote_person_onscreen state="APPROVED" last_approved_text="Bolgrun Stonesplitter, leader of the First Expeditionary Dwarfen Force to Athel Loren" last_edit_user="bob">Bolgrun Stonesplitter, leader of the First Expeditionary Dwarfen Force to Athel Loren</quote_person_onscreen>
</quotes_people>
<quotes_people record_uuid="{dbc0844a-68ef-46b2-8fff-1bfbcbb169d3}" record_timestamp="1441795574967" record_key="talgatha_the_fallen">
<quote_person_key>talgatha_the_fallen</quote_person_key>
<quote_person_onscreen state="APPROVED" last_approved_text="Tal'gatha the Fallen" last_edit_user="bob">Tal'gatha the Fallen</quote_person_onscreen>
</quotes_people>
<quotes_people record_uuid="{a54e0230-086a-4f3b-a98f-a1c5a62c4d97}" record_timestamp="1484910184337" record_key="thederic_de_maronz">
<quote_person_key>thederic_de_maronz</quote_person_key>
<quote_person_onscreen state="APPROVED" last_approved_text="Lord Thederic de Maronz, to a captured outlaw" last_edit_user="bob">Lord Thederic de Maronz, to a captured outlaw</quote_person_onscreen>
</quotes_people>
<quotes_people record_uuid="{b6c31e0c-f31c-42d4-96fc-3da364f4bc41}" record_timestamp="1441795574218" record_key="theoderic_gausser">
<quote_person_key>theoderic_gausser</quote_person_key>
<quote_person_onscreen state="APPROVED" last_approved_text="Theoderic Gausser, Elector Count of Nordland" last_edit_user="bob">Theoderic Gausser, Elector Count of Nordland</quote_person_onscreen>
</quotes_people>
<quotes_people record_uuid="{1b263974-8b5a-43f9-b8d1-b0101ebaec7c}" record_timestamp="1441117776858" record_key="thorgrim">
<quote_person_key>thorgrim</quote_person_key>
<quote_person_onscreen state="APPROVED" last_approved_text="Thorgrim Grudgebearer, Dwarfen High King" last_edit_user="bob">Thorgrim Grudgebearer, Dwarfen High King</quote_person_onscreen>
</quotes_people>
<quotes_people record_uuid="{fe14499b-669e-4ac9-896c-786c3f3aa83a}" record_timestamp="1441715082093" record_key="tobias_gottmann">
<quote_person_key>tobias_gottmann</quote_person_key>
<quote_person_onscreen state="APPROVED" last_approved_text="Tobias Gottmann, last survivor of the Altdorf Redshields" last_edit_user="bob">Tobias Gottmann, last survivor of the Altdorf Redshields</quote_person_onscreen>
</quotes_people>
<quotes_people record_uuid="{c1b766f1-aff5-412f-a8ef-1c38ace1a61b}" record_timestamp="1465373038683" record_key="udolf">
<quote_person_key>udolf</quote_person_key>
<quote_person_onscreen state="APPROVED" last_approved_text="Gunnery Captain Udolf Herzelman, his last words" last_edit_user="bob">Gunnery Captain Udolf Herzelman, his last words</quote_person_onscreen>
</quotes_people>
<quotes_people record_uuid="{29cd1d45-229b-4645-8da7-04b25bf602bd}" record_timestamp="1441795575591" record_key="ulfred_wasmeier">
<quote_person_key>ulfred_wasmeier</quote_person_key>
<quote_person_onscreen state="APPROVED" last_approved_text="Ulfred Wasmeier, Priest of Sigmar" last_edit_user="bob">Ulfred Wasmeier, Priest of Sigmar</quote_person_onscreen>
</quotes_people>
<quotes_people record_uuid="{dd8bcc39-c360-4fe5-94f2-81151df97246}" record_timestamp="1441716383243" record_key="vilitreska">
<quote_person_key>vilitreska</quote_person_key>
<quote_person_onscreen state="APPROVED" last_approved_text="Vilitreska, Lord of the Flux" last_edit_user="bob">Vilitreska, Lord of the Flux</quote_person_onscreen>
</quotes_people>
<quotes_people record_uuid="{b33e7137-0dd4-4479-9ccb-a2e65fbbc6eb}" record_timestamp="1441713778150" record_key="virtue_of_audacity">
<quote_person_key>virtue_of_audacity</quote_person_key>
<quote_person_onscreen state="APPROVED" last_approved_text="Virtue of Audacity" last_edit_user="bob">Virtue of Audacity</quote_person_onscreen>
</quotes_people>
<quotes_people record_uuid="{6d299726-3414-4a8f-82e9-c21c7889a9cd}" record_timestamp="1441713778134" record_key="virtue_of_confidence">
<quote_person_key>virtue_of_confidence</quote_person_key>
<quote_person_onscreen state="APPROVED" last_approved_text="Virtue of Confidence" last_edit_user="bob">Virtue of Confidence</quote_person_onscreen>
</quotes_people>
<quotes_people record_uuid="{b94055b3-8ffb-4a00-8131-4ecf33cac60a}" record_timestamp="1441713778056" record_key="virtue_of_discipline">
<quote_person_key>virtue_of_discipline</quote_person_key>
<quote_person_onscreen state="APPROVED" last_approved_text="Virtue of Discipline" last_edit_user="bob">Virtue of Discipline</quote_person_onscreen>
</quotes_people>
<quotes_people record_uuid="{8be8c052-192c-458f-97df-58f559f7000f}" record_timestamp="1441713778181" record_key="virtue_of_duty">
<quote_person_key>virtue_of_duty</quote_person_key>
<quote_person_onscreen state="APPROVED" last_approved_text="Virtue of Duty" last_edit_user="bob">Virtue of Duty</quote_person_onscreen>
</quotes_people>
<quotes_people record_uuid="{7a9b47e0-f306-4635-a1aa-7303cbb68581}" record_timestamp="1441713778275" record_key="virtue_of_empathy">
<quote_person_key>virtue_of_empathy</quote_person_key>
<quote_person_onscreen state="APPROVED" last_approved_text="Virtue of Empathy" last_edit_user="bob">Virtue of Empathy</quote_person_onscreen>
</quotes_people>
<quotes_people record_uuid="{2887d6ac-7408-4ae3-bbba-0e2ac1b5f507}" record_timestamp="1441713778259" record_key="virtue_of_heroism">
<quote_person_key>virtue_of_heroism</quote_person_key>
<quote_person_onscreen state="APPROVED" last_approved_text="Virtue of Heroism" last_edit_user="bob">Virtue of Heroism</quote_person_onscreen>
</quotes_people>
<quotes_people record_uuid="{031f8667-439f-4cdc-a2de-b296fa7ff1db}" record_timestamp="1441713778228" record_key="virtue_of_knightly_temper">
<quote_person_key>virtue_of_knightly_temper</quote_person_key>
<quote_person_onscreen state="APPROVED" last_approved_text="Virtue of Knightly Temper" last_edit_user="bob">Virtue of Knightly Temper</quote_person_onscreen>
</quotes_people>
<quotes_people record_uuid="{ccc70b65-f81a-41f8-bbcb-af571c233ce0}" record_timestamp="1441713778119" record_key="virtue_of_noble_disdain">
<quote_person_key>virtue_of_noble_disdain</quote_person_key>
<quote_person_onscreen state="APPROVED" last_approved_text="Virtue of Noble Disdain" last_edit_user="bob">Virtue of Noble Disdain</quote_person_onscreen>
</quotes_people>
<quotes_people record_uuid="{bd30e537-a3d2-43ee-8e3a-335591931edb}" record_timestamp="1441716218951" record_key="virtue_of_purity">
<quote_person_key>virtue_of_purity</quote_person_key>
<quote_person_onscreen state="APPROVED" last_approved_text="Virtue of Purity " last_edit_user="bob">Virtue of Purity </quote_person_onscreen>
</quotes_people>
<quotes_people record_uuid="{8523dc27-9b1c-4918-8f45-b822836f2b9b}" record_timestamp="1441713778228" record_key="virtue_of_stoicism">
<quote_person_key>virtue_of_stoicism</quote_person_key>
<quote_person_onscreen state="APPROVED" last_approved_text="Virtue of Stoicism" last_edit_user="bob">Virtue of Stoicism</quote_person_onscreen>
</quotes_people>
<quotes_people record_uuid="{8a7b6a8c-47c7-4bb3-9138-f56689f11429}" record_timestamp="1441713778212" record_key="virtue_of_the_ideal">
<quote_person_key>virtue_of_the_ideal</quote_person_key>
<quote_person_onscreen state="APPROVED" last_approved_text="Virtue of the Ideal" last_edit_user="bob">Virtue of the Ideal</quote_person_onscreen>
</quotes_people>
<quotes_people record_uuid="{1566b2bd-6e21-4ad7-ab03-616c0d946267}" record_timestamp="1441713778244" record_key="virtue_of_the_impetuous_knight">
<quote_person_key>virtue_of_the_impetuous_knight</quote_person_key>
<quote_person_onscreen state="APPROVED" last_approved_text="Virtue of the Impetuous Knight" last_edit_user="bob">Virtue of the Impetuous Knight</quote_person_onscreen>
</quotes_people>
<quotes_people record_uuid="{77634059-5b09-411f-87db-988d841b053c}" record_timestamp="1441713778103" record_key="virtue_of_the_joust">
<quote_person_key>virtue_of_the_joust</quote_person_key>
<quote_person_onscreen state="APPROVED" last_approved_text="Virtue of the Joust" last_edit_user="bob">Virtue of the Joust</quote_person_onscreen>
</quotes_people>
<quotes_people record_uuid="{c5be59a2-1a26-4f6f-bedd-10a3733f073e}" record_timestamp="1441713778166" record_key="virtue_of_the_penitent">
<quote_person_key>virtue_of_the_penitent</quote_person_key>
<quote_person_onscreen state="APPROVED" last_approved_text="Virtue of the Penitent" last_edit_user="bob">Virtue of the Penitent</quote_person_onscreen>
</quotes_people>
<quotes_people record_uuid="{6b56af58-75c5-49ca-9571-3e12f26172ca}" record_timestamp="1441795574499" record_key="vlad_von_carstein">
<quote_person_key>vlad_von_carstein</quote_person_key>
<quote_person_onscreen state="APPROVED" last_approved_text="Vlad von Carstein" last_edit_user="bob">Vlad von Carstein</quote_person_onscreen>
</quotes_people>
<quotes_people record_uuid="{848263b9-f225-4dae-a1a7-19ba581134b6}" record_timestamp="1441795575419" record_key="volkmar">
<quote_person_key>volkmar</quote_person_key>
<quote_person_onscreen state="APPROVED" last_approved_text="Volkmar, Theogonist of Sigmar" last_edit_user="bob">Volkmar, Theogonist of Sigmar</quote_person_onscreen>
</quotes_people>
<quotes_people record_uuid="{b4d4d352-3cd1-474b-805f-b62787132509}" record_timestamp="1441795576496" record_key="warlord_hroth">
<quote_person_key>warlord_hroth</quote_person_key>
<quote_person_onscreen state="APPROVED" last_approved_text="Warlord Hroth" last_edit_user="bob">Warlord Hroth</quote_person_onscreen>
</quotes_people>
<quotes_people record_uuid="{0c8a7254-059c-4585-9e5e-de35b70e1189}" record_timestamp="1441795575029" record_key="witch_hunter_motto">
<quote_person_key>witch_hunter_motto</quote_person_key>
<quote_person_onscreen state="APPROVED" last_approved_text="Witch Hunter motto" last_edit_user="bob">Witch Hunter motto</quote_person_onscreen>
</quotes_people>
<quotes_people record_uuid="{094e0efa-1694-4ca2-aebd-bcf1ea66d649}" record_timestamp="1477038106564" record_key="woodwhisper">
<quote_person_key>woodwhisper</quote_person_key>
<quote_person_onscreen state="APPROVED" last_approved_text="Elui Woodwhisper, Prophet and Scribe to the Phoenix King" last_edit_user="bob">Elui Woodwhisper, Prophet and Scribe to the Phoenix King</quote_person_onscreen>
</quotes_people>
<quotes_people record_uuid="{3e2cf2d9-a513-44e9-8641-66b5897f2e27}" record_timestamp="1441716619131" record_key="wulfrick">
<quote_person_key>wulfrick</quote_person_key>
<quote_person_onscreen state="APPROVED" last_approved_text="Wulfrik the Wanderer, to Dwarf King Thurbad Stonebeard, in perfect Khazalid" last_edit_user="bob">Wulfrik the Wanderer, to Dwarf King Thurbad Stonebeard, in perfect Khazalid</quote_person_onscreen>
</quotes_people>
<quotes_people record_uuid="{7599cbe2-9773-4bb4-b388-62c419e9456f}" record_timestamp="1441714324077" record_key="yinlinsson">
<quote_person_key>yinlinsson</quote_person_key>
<quote_person_onscreen state="APPROVED" last_approved_text="Traditional Yinlinsson war cry" last_edit_user="bob">Traditional Yinlinsson war cry</quote_person_onscreen>
</quotes_people>
<quotes_people record_uuid="{11f7057e-7296-476a-b478-9dcb9b8bd773}" record_timestamp="1444404885817" record_key="zacharias_the_everlasting">
<quote_person_key>zacharias_the_everlasting</quote_person_key>
<quote_person_onscreen state="APPROVED" last_approved_text="Zacharias the Everliving" last_edit_user="bob">Zacharias the Everliving</quote_person_onscreen>
</quotes_people>
<quotes_people record_uuid="{db8dc5bc-d7ef-4065-ab60-32542769b082}" record_timestamp="1441795574842" record_key="zalesh">
<quote_person_key>zalesh</quote_person_key>
<quote_person_onscreen state="APPROVED" last_approved_text="Zalesh, Chaos Chosen" last_edit_user="bob">Zalesh, Chaos Chosen</quote_person_onscreen>
</quotes_people>
<quotes_people record_uuid="{73fe337e-d780-4dea-88aa-4fc298d42973}" record_timestamp="1445524200830" record_key="zar_sezask">
<quote_person_key>zar_sezask</quote_person_key>
<quote_person_onscreen state="APPROVED" last_approved_text="Zar Sezask, Kurgan Chieftain" last_edit_user="bob">Zar Sezask, Kurgan Chieftain</quote_person_onscreen>
</quotes_people>
<quotes_people record_uuid="{07a1ffbf-d14f-4fa1-9ef2-eb53c2695a9d}" record_timestamp="1445524200870" record_key="zar_uzelek">
<quote_person_key>zar_uzelek</quote_person_key>
<quote_person_onscreen state="APPROVED" last_approved_text="Zar Uzelek, Yusak Chieftain" last_edit_user="bob">Zar Uzelek, Yusak Chieftain</quote_person_onscreen>
</quotes_people>
</dataroot>
