<?xml version="1.0" encoding="UTF-8" standalone="no"?>
<!DOCTYPE TWaD_effect_bundles>
<root>
<edit_uuid>d951a119-ab6f-4ae2-aca2-332528fa1534</edit_uuid>
<agf_special_dependencies>+wh_main_food_bundle_horde_infighting,+wh_main_food_bundle_faction_positive,+wh_main_food_bundle_faction_negative,+wh_main_food_bundle_faction_positive_province_negative,+wh_main_food_bundle_province_negative,+wh_main_food_bundle_horde_faction_positive,+wh_main_food_bundle_horde_faction_negative,+wh_main_food_bundle_faction_positive_host_negative,+wh_main_food_bundle_horde_host_negative</agf_special_dependencies>
<field>
<field_uuid>{b458c1b6-b79f-41e2-ba25-a4bd62b9f9ea}</field_uuid>
<primary_key>1</primary_key>
<name>key</name>
<field_type>text</field_type>
<required>1</required>
<max_length>255</max_length>
<encyclopaedia_export>1</encyclopaedia_export>
<agf_link_to_dependency>0</agf_link_to_dependency>
<agf_link_to_dependents>0</agf_link_to_dependents>
<agf_done>0</agf_done>
<requires_startpos_reprocess>0</requires_startpos_reprocess>
<requires_campaign_map_reprocess>0</requires_campaign_map_reprocess>
</field>
<field>
<field_uuid>{7471cc8b-01fe-43bf-8e27-38db1e0bc18f}</field_uuid>
<primary_key>0</primary_key>
<name>localised_title</name>
<field_type>text</field_type>
<required>1</required>
<max_length>255</max_length>
<encyclopaedia_export>1</encyclopaedia_export>
<agf_link_to_dependency>0</agf_link_to_dependency>
<agf_link_to_dependents>0</agf_link_to_dependents>
<agf_done>0</agf_done>
<requires_startpos_reprocess>0</requires_startpos_reprocess>
<requires_campaign_map_reprocess>0</requires_campaign_map_reprocess>
</field>
<field>
<field_uuid>{cf6fe78d-ab83-43c5-8fbf-bf6bb396756f}</field_uuid>
<primary_key>0</primary_key>
<name>localised_description</name>
<field_type>text</field_type>
<required>1</required>
<max_length>255</max_length>
<encyclopaedia_export>1</encyclopaedia_export>
<agf_link_to_dependency>0</agf_link_to_dependency>
<agf_link_to_dependents>0</agf_link_to_dependents>
<agf_done>0</agf_done>
<requires_startpos_reprocess>0</requires_startpos_reprocess>
<requires_campaign_map_reprocess>0</requires_campaign_map_reprocess>
</field>
<field>
<field_uuid>{24e35e91-927f-49c4-a14f-f37e8ec96c30}</field_uuid>
<primary_key>0</primary_key>
<name>ui_icon</name>
<field_type>text</field_type>
<is_filename>1</is_filename>
<filename_relative_path>ui/campaign ui/effect_bundles/%</filename_relative_path>
<required>1</required>
<max_length>255</max_length>
<encyclopaedia_export>1</encyclopaedia_export>
<agf_link_to_dependency>0</agf_link_to_dependency>
<agf_link_to_dependents>0</agf_link_to_dependents>
<agf_done>0</agf_done>
<requires_startpos_reprocess>0</requires_startpos_reprocess>
<requires_campaign_map_reprocess>0</requires_campaign_map_reprocess>
</field>
<field>
<field_uuid>{70ba0e85-126b-447a-a0dc-9143ac18f66f}</field_uuid>
<primary_key>0</primary_key>
<name>bundle_target</name>
<field_type>text</field_type>
<required>1</required>
<default_value>faction</default_value>
<max_length>255</max_length>
<column_source_column>key</column_source_column>
<column_source_table>effect_bundle_targets</column_source_table>
<encyclopaedia_export>1</encyclopaedia_export>
<agf_link_to_dependency>1</agf_link_to_dependency>
<agf_link_to_dependents>0</agf_link_to_dependents>
<agf_done>1</agf_done>
<requires_startpos_reprocess>0</requires_startpos_reprocess>
<requires_campaign_map_reprocess>0</requires_campaign_map_reprocess>
</field>
</root>
