<?xml version="1.0" encoding="UTF-8"?>
<dataroot xmlns:od="urn:schemas-microsoft-com:officedata" xmlns:xsi="http://www.w3.org/2001/XMLSchema-instance" xsi:noNamespaceSchemaLocation="ui_tagged_images.xsd" export_time="Thu Feb 16 11:49:09 2017" revision="50" export_branch="T:/branches/warhammer/bret/warhammer/binaries.x64" export_user="bob">
<edit_uuid>b23b1d07-e62b-4681-ada9-6cc4084effbd</edit_uuid>
<ui_tagged_images record_uuid="{3a56d15f-5920-4afe-893c-a8ae89da3372}" record_timestamp="1470821044049" record_key="brt_artois">
<image_path>UI/Flags/wh_main_brt_artois/mon_24.png</image_path>
<key>brt_artois</key>
</ui_tagged_images>
<ui_tagged_images record_uuid="{c19cc45f-1c24-4ad9-9e6f-912365795868}" record_timestamp="1470821044049" record_key="brt_bastonne">
<image_path>UI/Flags/wh_main_brt_bastonne/mon_24.png</image_path>
<key>brt_bastonne</key>
</ui_tagged_images>
<ui_tagged_images record_uuid="{c71e6329-c86c-4d1b-965b-9303c061e43b}" record_timestamp="1470821044049" record_key="brt_bordeleaux">
<image_path>UI/Flags/wh_main_brt_bordeleaux/mon_24.png</image_path>
<key>brt_bordeleaux</key>
</ui_tagged_images>
<ui_tagged_images record_uuid="{6cf3cb69-7c96-4c25-9de6-f16fd20ea293}" record_timestamp="1481825202829" record_key="brt_bretonnia">
<image_path>UI/Flags/wh_main_brt_bretonnia/mon_24.png</image_path>
<key>brt_bretonnia</key>
</ui_tagged_images>
<ui_tagged_images record_uuid="{db5036c5-a9c4-479d-b130-9278c5c9b1a7}" record_timestamp="1470821044049" record_key="brt_carcassonne">
<image_path>UI/Flags/wh_main_brt_carcassonne/mon_24.png</image_path>
<key>brt_carcassonne</key>
</ui_tagged_images>
<ui_tagged_images record_uuid="{6fea0b83-4cc8-4ae2-9dc4-ad11c9e6f501}" record_timestamp="1470821044049" record_key="brt_lyonesse">
<image_path>UI/Flags/wh_main_brt_lyonesse/mon_24.png</image_path>
<key>brt_lyonesse</key>
</ui_tagged_images>
<ui_tagged_images record_uuid="{3731d942-d751-473d-9175-1129e45e773c}" record_timestamp="1470821044049" record_key="brt_mousillon">
<image_path>UI/Flags/wh_main_vmp_mousillon/mon_24.png</image_path>
<key>brt_mousillon</key>
</ui_tagged_images>
<ui_tagged_images record_uuid="{80cc8282-747c-4d04-a9e7-3cb8081eef8d}" record_timestamp="1470821044049" record_key="brt_parravon">
<image_path>UI/Flags/wh_main_brt_parravon/mon_24.png</image_path>
<key>brt_parravon</key>
</ui_tagged_images>
<ui_tagged_images record_uuid="{88f09989-dec5-40fa-8641-bdf01451e1da}" record_timestamp="1482329655849" record_key="bullet_brt_chivalry">
<image_path>UI/Frontend UI/faction_bullets/bullet_brt_chivalry.png</image_path>
<key>bullet_brt_chivalry</key>
</ui_tagged_images>
<ui_tagged_images record_uuid="{9827ac79-2457-4f53-824d-d7d89031a224}" record_timestamp="1482329655927" record_key="bullet_brt_peasants">
<image_path>UI/Frontend UI/faction_bullets/bullet_brt_peasants.png</image_path>
<key>bullet_brt_peasants</key>
</ui_tagged_images>
<ui_tagged_images record_uuid="{d01a24fd-aefc-4655-9d99-00fdcea05bf2}" record_timestamp="1482329655776" record_key="bullet_brt_units">
<image_path>UI/Frontend UI/faction_bullets/bullet_brt_units.png</image_path>
<key>bullet_brt_units</key>
</ui_tagged_images>
<ui_tagged_images record_uuid="{b44cc142-73bb-4149-8146-bb3e8e98748c}" record_timestamp="1477038873879" record_key="bullet_bst_beastpath">
<image_path>UI/Frontend UI/faction_bullets/bullet_bst_beastpaths.png</image_path>
<key>bullet_bst_beastpath</key>
</ui_tagged_images>
<ui_tagged_images record_uuid="{51aefe12-4e17-4e25-bf1a-b6dd2ac47a0c}" record_timestamp="1477038873882" record_key="bullet_bst_moon">
<image_path>UI/Frontend UI/faction_bullets/bullet_bst_the_dark_moon.png</image_path>
<key>bullet_bst_moon</key>
</ui_tagged_images>
<ui_tagged_images record_uuid="{31239095-dd03-4131-936a-ba710fb53624}" record_timestamp="1477038873881" record_key="bullet_bst_units">
<image_path>UI/Frontend UI/faction_bullets/bullet_bst_units.png</image_path>
<key>bullet_bst_units</key>
</ui_tagged_images>
<ui_tagged_images record_uuid="{2f3fdc67-9e5c-4f95-b6a5-bce99e05ea0b}" record_timestamp="1477038873871" record_key="bullet_chs_awaken">
<image_path>UI/Frontend UI/faction_bullets/bullet_chs_awaken_tribes.png</image_path>
<key>bullet_chs_awaken</key>
</ui_tagged_images>
<ui_tagged_images record_uuid="{e595c656-485d-4a4d-aa88-3b5629e0bbfe}" record_timestamp="1477038873870" record_key="bullet_chs_corruption">
<image_path>UI/Frontend UI/faction_bullets/bullet_chs_corruption.png</image_path>
<key>bullet_chs_corruption</key>
</ui_tagged_images>
<ui_tagged_images record_uuid="{84d7ebe0-3b49-4997-87f9-e91539bba8fb}" record_timestamp="1477038873873" record_key="bullet_chs_units">
<image_path>UI/Frontend UI/faction_bullets/bullet_chs_units.png</image_path>
<key>bullet_chs_units</key>
</ui_tagged_images>
<ui_tagged_images record_uuid="{b72f9f6a-1e3e-4a8c-99d4-491e90fb3ffa}" record_timestamp="1477038873872" record_key="bullet_dwf_ancestors">
<image_path>UI/Frontend UI/faction_bullets/bullet_dwf_angrund_ancestors.png</image_path>
<key>bullet_dwf_ancestors</key>
</ui_tagged_images>
<ui_tagged_images record_uuid="{fa1108ba-1d03-4681-90a0-00304ef5f661}" record_timestamp="1477038873876" record_key="bullet_dwf_grudges">
<image_path>UI/Frontend UI/faction_bullets/bullet_dwf_grudges.png</image_path>
<key>bullet_dwf_grudges</key>
</ui_tagged_images>
<ui_tagged_images record_uuid="{dccdb129-ab97-41cd-b8a7-8bd8fd3923ec}" record_timestamp="1477038873875" record_key="bullet_dwf_underway">
<image_path>UI/Frontend UI/faction_bullets/bullet_dwf_underway.png</image_path>
<key>bullet_dwf_underway</key>
</ui_tagged_images>
<ui_tagged_images record_uuid="{9a9976e2-7d38-4068-918e-1ef6ab6156c1}" record_timestamp="1477038873878" record_key="bullet_dwf_units">
<image_path>UI/Frontend UI/faction_bullets/bullet_dwf_units.png</image_path>
<key>bullet_dwf_units</key>
</ui_tagged_images>
<ui_tagged_images record_uuid="{1ca83b19-3f44-4bc9-a01d-ecbb72fa0612}" record_timestamp="1477038873877" record_key="bullet_emp_magic">
<image_path>UI/Frontend UI/faction_bullets/bullet_emp_colleges_of_magic.png</image_path>
<key>bullet_emp_magic</key>
</ui_tagged_images>
<ui_tagged_images record_uuid="{d31a720e-100d-49de-986d-71d25d3261e2}" record_timestamp="1477038873885" record_key="bullet_emp_offices">
<image_path>UI/Frontend UI/faction_bullets/bullet_emp_offices.png</image_path>
<key>bullet_emp_offices</key>
</ui_tagged_images>
<ui_tagged_images record_uuid="{43da3f40-2359-4043-978f-52f53c86a24c}" record_timestamp="1477038873884" record_key="bullet_emp_units">
<image_path>UI/Frontend UI/faction_bullets/bullet_emp_units.png</image_path>
<key>bullet_emp_units</key>
</ui_tagged_images>
<ui_tagged_images record_uuid="{f6975b46-288d-42df-a3b6-2ea089ab0c0a}" record_timestamp="1477038873888" record_key="bullet_grn_karak">
<image_path>UI/Frontend UI/faction_bullets/bullet_grn_eight_peaks.png</image_path>
<key>bullet_grn_karak</key>
</ui_tagged_images>
<ui_tagged_images record_uuid="{5804e6ef-b08a-45f4-8bfb-88a5c4a029d7}" record_timestamp="1477038873887" record_key="bullet_grn_savage">
<image_path>UI/Frontend UI/faction_bullets/bullet_grn_savage_orcs.png</image_path>
<key>bullet_grn_savage</key>
</ui_tagged_images>
<ui_tagged_images record_uuid="{3f89621f-a223-4349-881a-c4427f14521e}" record_timestamp="1477038873890" record_key="bullet_grn_units">
<image_path>UI/Frontend UI/faction_bullets/bullet_grn_units.png</image_path>
<key>bullet_grn_units</key>
</ui_tagged_images>
<ui_tagged_images record_uuid="{fbfd347c-ba49-48c0-a124-6f33466ba3d9}" record_timestamp="1477038873889" record_key="bullet_grn_waaagh">
<image_path>UI/Frontend UI/faction_bullets/bullet_grn_waaagh.png</image_path>
<key>bullet_grn_waaagh</key>
</ui_tagged_images>
<ui_tagged_images record_uuid="{bf289432-008f-46e3-b767-85142653ccc6}" record_timestamp="1477038873892" record_key="bullet_vmp_corruption">
<image_path>UI/Frontend UI/faction_bullets/bullet_vmp_corruption.png</image_path>
<key>bullet_vmp_corruption</key>
</ui_tagged_images>
<ui_tagged_images record_uuid="{87c69984-431e-4380-9fc9-49bc0ee33bcd}" record_timestamp="1477038873891" record_key="bullet_vmp_dead">
<image_path>UI/Frontend UI/faction_bullets/bullet_vmp_raise_dead.png</image_path>
<key>bullet_vmp_dead</key>
</ui_tagged_images>
<ui_tagged_images record_uuid="{9e52165f-6a9c-4e4a-beed-04fadbf4fe00}" record_timestamp="1483529761724" record_key="bullet_vmp_love">
<image_path>UI/Frontend UI/faction_bullets/bullet_vmp_love.png</image_path>
<key>bullet_vmp_love</key>
</ui_tagged_images>
<ui_tagged_images record_uuid="{42b1532f-9c9b-4a80-b4da-532edd0ea07b}" record_timestamp="1477038873883" record_key="bullet_vmp_units">
<image_path>UI/Frontend UI/faction_bullets/bullet_vmp_units.png</image_path>
<key>bullet_vmp_units</key>
</ui_tagged_images>
<ui_tagged_images record_uuid="{e249d199-3c5f-4c0c-af0d-72b300f5f705}" record_timestamp="1479313899366" record_key="bullet_wef_amber">
<image_path>UI/Frontend UI/faction_bullets/bullet_wef_amber.png</image_path>
<key>bullet_wef_amber</key>
</ui_tagged_images>
<ui_tagged_images record_uuid="{4c467660-e839-46b0-92d1-77b90375c8ec}" record_timestamp="1479313899368" record_key="bullet_wef_council">
<image_path>UI/Frontend UI/faction_bullets/bullet_wef_council.png</image_path>
<key>bullet_wef_council</key>
</ui_tagged_images>
<ui_tagged_images record_uuid="{02417998-130a-4ae2-9eaf-eff384b4ea03}" record_timestamp="1479313899369" record_key="bullet_wef_tree_council">
<image_path>UI/Frontend UI/faction_bullets/bullet_wef_tree_council.png</image_path>
<key>bullet_wef_tree_council</key>
</ui_tagged_images>
<ui_tagged_images record_uuid="{4dc522af-b40f-4318-8379-1a28d6954e4a}" record_timestamp="1479313899370" record_key="bullet_wef_units">
<image_path>UI/Frontend UI/faction_bullets/bullet_wef_units.png</image_path>
<key>bullet_wef_units</key>
</ui_tagged_images>
<ui_tagged_images record_uuid="{39ef8fd7-0f21-4a72-952a-0588ca2c95ac}" record_timestamp="1481037394767" record_key="bullet_wef_units_monstrous">
<image_path>UI/Frontend UI/faction_bullets/bullet_wef_units_monstrous.png</image_path>
<key>bullet_wef_units_monstrous</key>
</ui_tagged_images>
<ui_tagged_images record_uuid="{3d076ea3-ee6c-4368-a1a7-fa7d73ab987d}" record_timestamp="1479313899371" record_key="bullet_wef_worldroots">
<image_path>UI/Frontend UI/faction_bullets/bullet_wef_worldroots.png</image_path>
<key>bullet_wef_worldroots</key>
</ui_tagged_images>
<ui_tagged_images record_uuid="{fe293263-e46b-4fae-b427-b0aa324c1556}" record_timestamp="1446125405007" record_key="icon_admiral">
<image_path>ui/skins/default/icon_navy.png</image_path>
<key>icon_admiral</key>
</ui_tagged_images>
<ui_tagged_images record_uuid="{97934022-bb1e-4b23-8305-5012e6938af0}" record_timestamp="1487245749205" record_key="icon_amber">
<image_path>ui/skins/default/icon_amber.png</image_path>
<key>icon_amber</key>
</ui_tagged_images>
<ui_tagged_images record_uuid="{830b12d9-29ba-46c1-b03b-9e0accf4a71e}" record_timestamp="1452078503873" record_key="icon_ambush_stance">
<image_path>ui/skins/default/icon_stance_ambush.png</image_path>
<key>icon_ambush_stance</key>
</ui_tagged_images>
<ui_tagged_images record_uuid="{847e2bd1-fbb8-4b17-bed8-84b664e81e66}" record_timestamp="1464176218326" record_key="icon_ammo">
<image_path>ui/skins/default/icon_stat_ammo.png</image_path>
<key>icon_ammo</key>
</ui_tagged_images>
<ui_tagged_images record_uuid="{75a3e8f8-89a5-4ba3-a679-f0ec23f1c127}" record_timestamp="1464176218316" record_key="icon_ap">
<image_path>ui/skins/default/modifier_icon_armour_piercing.png</image_path>
<key>icon_ap</key>
</ui_tagged_images>
<ui_tagged_images record_uuid="{cb9e69c9-d292-4f0d-976e-b8194d2fe4cb}" record_timestamp="1467718214676" record_key="icon_ap_ranged">
<image_path>ui/skins/default/modifier_icon_armour_piercing_ranged.png</image_path>
<key>icon_ap_ranged</key>
</ui_tagged_images>
<ui_tagged_images record_uuid="{385679cb-fef7-47ed-a15b-aabd0377e697}" record_timestamp="1468499471624" record_key="icon_armour">
<image_path>ui/skins/default/icon_stat_armour.png</image_path>
<key>icon_armour</key>
</ui_tagged_images>
<ui_tagged_images record_uuid="{a38fc5d5-a16a-4f50-aa05-a1fb421f4289}" record_timestamp="1468497307897" record_key="icon_arrow_down">
<image_path>ui/skins/default/ua_arrow_decrease_1.png</image_path>
<key>icon_arrow_down</key>
</ui_tagged_images>
<ui_tagged_images record_uuid="{66f5810a-9561-48eb-8e8a-7f3cacfd1360}" record_timestamp="1468497307897" record_key="icon_arrow_up">
<image_path>ui/skins/default/ua_arrow_increase_1.png</image_path>
<key>icon_arrow_up</key>
</ui_tagged_images>
<ui_tagged_images record_uuid="{8235ad16-5450-4801-977c-196a4518be99}" record_timestamp="1468497307898" record_key="icon_arrow_upgrade">
<image_path>ui/skins/default/ua_winds_of_magic_upgraded_icon.png</image_path>
<key>icon_arrow_upgrade</key>
</ui_tagged_images>
<ui_tagged_images record_uuid="{f911d763-2b20-4de3-932d-d0560cf63c1e}" record_timestamp="1447331500609" record_key="icon_attrition">
<image_path>ui/skins/default/replenish_icon_attrition.png</image_path>
<key>icon_attrition</key>
</ui_tagged_images>
<ui_tagged_images record_uuid="{24dfdf11-a96f-4ca8-8808-9f9277235ccc}" record_timestamp="1456912722019" record_key="icon_battle_site">
<image_path>ui/skins/default/icon_raise_dead_small.png</image_path>
<key>icon_battle_site</key>
</ui_tagged_images>
<ui_tagged_images record_uuid="{af03c48e-0d92-483d-b871-b9cfd413dfea}" record_timestamp="1464021098323" record_key="icon_bestial_rage">
<image_path>UI\skins\wh_dlc03_bst_beastmen\icon_army_morale.png</image_path>
<key>icon_bestial_rage</key>
</ui_tagged_images>
<ui_tagged_images record_uuid="{7f6fb085-b219-42ea-8538-ce5a3b81c958}" record_timestamp="1463569327290" record_key="icon_charge">
<image_path>ui/skins/default/icon_stat_charge_bonus.png</image_path>
<key>icon_charge</key>
</ui_tagged_images>
<ui_tagged_images record_uuid="{9f38b426-496a-4a01-9b84-0c679ee9943c}" record_timestamp="1487245749250" record_key="icon_chivalry">
<image_path>ui/skins/wh_main_brt_bretonnia/icon_chivalry.png</image_path>
<key>icon_chivalry</key>
</ui_tagged_images>
<ui_tagged_images record_uuid="{66756588-f997-41b9-bb7e-67d7b1d5940b}" record_timestamp="1462358725705" record_key="icon_confederation">
<image_path>ui/skins/default/treaty_confederation.png</image_path>
<key>icon_confederation</key>
</ui_tagged_images>
<ui_tagged_images record_uuid="{30b53a65-9a02-4101-9679-644fba1253d4}" record_timestamp="1442919703445" record_key="icon_corruption_chs">
<image_path>ui/skins/default/icon_corruption_chs.png</image_path>
<key>icon_corruption_chs</key>
</ui_tagged_images>
<ui_tagged_images record_uuid="{b9bf7830-fc74-411e-a591-46ec95e56ea6}" record_timestamp="1460466421568" record_key="icon_corruption_untainted">
<image_path>ui/skins/default/icon_corruption_untainted.png</image_path>
<key>icon_corruption_untainted</key>
</ui_tagged_images>
<ui_tagged_images record_uuid="{6baa1ea5-ee25-46ac-88d5-b2bca8ae0764}" record_timestamp="1442919703461" record_key="icon_corruption_vmp">
<image_path>ui/skins/default/icon_corruption_vmp.png</image_path>
<key>icon_corruption_vmp</key>
</ui_tagged_images>
<ui_tagged_images record_uuid="{25452aa8-8112-4192-b3c1-5b6a75d89aa6}" record_timestamp="1462358725704" record_key="icon_defensive_alliance">
<image_path>ui/skins/default/treaty_defensive_alliance.png</image_path>
<key>icon_defensive_alliance</key>
</ui_tagged_images>
<ui_tagged_images record_uuid="{ec779a59-0c98-413b-a596-eb9b0547bf37}" record_timestamp="1468497308472" record_key="icon_dmg_flaming">
<image_path>ui/skins/default/modifier_icon_flaming.png</image_path>
<key>icon_dmg_flaming</key>
</ui_tagged_images>
<ui_tagged_images record_uuid="{abfc1765-8722-49c1-a928-79035431ea94}" record_timestamp="1468497308471" record_key="icon_dmg_magical">
<image_path>ui/skins/default/modifier_icon_magical.png</image_path>
<key>icon_dmg_magical</key>
</ui_tagged_images>
<ui_tagged_images record_uuid="{443213bb-5f91-4c03-a37a-2d9db551c17b}" record_timestamp="1481902948647" record_key="icon_effect_archer">
<image_path>UI/Campaign UI/Effect_bundles/archer.png</image_path>
<key>icon_effect_archer</key>
</ui_tagged_images>
<ui_tagged_images record_uuid="{a8c64989-37b9-4450-a6e9-210c8c2fbd82}" record_timestamp="1477035619105" record_key="icon_effect_army">
<image_path>UI/Campaign UI/Effect_bundles/army.png</image_path>
<key>icon_effect_army</key>
</ui_tagged_images>
<ui_tagged_images record_uuid="{b1c2b23e-555d-400f-a6aa-e50373930b8b}" record_timestamp="1477035619099" record_key="icon_effect_cash">
<image_path>UI/Campaign UI/Effect_bundles/military_spending.png</image_path>
<key>icon_effect_cash</key>
</ui_tagged_images>
<ui_tagged_images record_uuid="{9b8f0ff9-53a8-4469-be9b-5ff1a7add548}" record_timestamp="1477035619118" record_key="icon_effect_charge">
<image_path>UI/Campaign UI/Effect_bundles/charge.png</image_path>
<key>icon_effect_charge</key>
</ui_tagged_images>
<ui_tagged_images record_uuid="{58ad3ff7-7a13-4563-88ea-f73a3dacb262}" record_timestamp="1477035619099" record_key="icon_effect_construction">
<image_path>UI/Campaign UI/Effect_bundles/construction.png</image_path>
<key>icon_effect_construction</key>
</ui_tagged_images>
<ui_tagged_images record_uuid="{a4a44c1b-c3ad-4963-944a-c2e59af32687}" record_timestamp="1477035619100" record_key="icon_effect_hero">
<image_path>UI/Campaign UI/Effect_bundles/spy.png</image_path>
<key>icon_effect_hero</key>
</ui_tagged_images>
<ui_tagged_images record_uuid="{536db344-771d-4d59-9a5b-d21d69f647d7}" record_timestamp="1477035619099" record_key="icon_effect_morale">
<image_path>UI/Campaign UI/Effect_bundles/morale.png</image_path>
<key>icon_effect_morale</key>
</ui_tagged_images>
<ui_tagged_images record_uuid="{6adfa8b3-700b-4eca-93dc-54b4eae88ef3}" record_timestamp="1477035619105" record_key="icon_effect_treasury">
<image_path>UI/Campaign UI/Effect_bundles/treasury.png</image_path>
<key>icon_effect_treasury</key>
</ui_tagged_images>
<ui_tagged_images record_uuid="{78616349-796d-46e5-b68c-daaef3dddef8}" record_timestamp="1452078504014" record_key="icon_encamp_stance">
<image_path>ui/skins/default/icon_stance_encamp.png</image_path>
<key>icon_encamp_stance</key>
</ui_tagged_images>
<ui_tagged_images record_uuid="{e2a34bf3-f2d8-4418-bc0c-08ad391db8f4}" record_timestamp="1436966067452" record_key="icon_fealty">
<image_path>ui/skins/default/icon_ambition.png</image_path>
<key>icon_fealty</key>
</ui_tagged_images>
<ui_tagged_images record_uuid="{26983be6-d707-4d46-ae8d-193bf999e6d2}" record_timestamp="1446125006989" record_key="icon_fightiness">
<image_path>ui/skins/default/icon_army_morale.png</image_path>
<key>icon_fightiness</key>
</ui_tagged_images>
<ui_tagged_images record_uuid="{7244b2cd-54bf-4831-a833-ab6e9c710c94}" record_timestamp="1479317172005" record_key="icon_food">
<image_path>ui/skins/default/icon_amber.png</image_path>
<key>icon_food</key>
</ui_tagged_images>
<ui_tagged_images record_uuid="{86ee0a55-c914-4a4c-9075-8cff9bf859fc}" record_timestamp="1442995474063" record_key="icon_general">
<image_path>ui/skins/default/icon_army.png</image_path>
<key>icon_general</key>
</ui_tagged_images>
<ui_tagged_images record_uuid="{1df75c59-054f-48c5-9d67-27b5ea470524}" record_timestamp="1484735648877" record_key="icon_green_knight">
<image_path>UI/Common UI/unit_category_icons/wh_dlc07_brt_green_knight.png</image_path>
<key>icon_green_knight</key>
</ui_tagged_images>
<ui_tagged_images record_uuid="{caf4068c-a234-4117-93b4-0566c1b3fdba}" record_timestamp="1447077593490" record_key="icon_growth">
<image_path>ui/skins/default/icon_growth.png</image_path>
<key>icon_growth</key>
</ui_tagged_images>
<ui_tagged_images record_uuid="{5e9d3414-640b-481e-83ba-4d5327f1d803}" record_timestamp="1446543714585" record_key="icon_hero">
<image_path>ui/skins/default/icon_agent_small.png</image_path>
<key>icon_hero</key>
</ui_tagged_images>
<ui_tagged_images record_uuid="{76a755cd-25ee-444d-a2c5-12b69ff83ba1}" record_timestamp="1466591743604" record_key="icon_hidden_encampment">
<image_path>ui/skins/default/icon_stance_encamp.png</image_path>
<key>icon_hidden_encampment</key>
</ui_tagged_images>
<ui_tagged_images record_uuid="{4082b24a-480e-4d87-9c43-d1ff02026a84}" record_timestamp="1463569484746" record_key="icon_hp">
<image_path>ui/skins/default/icon_stat_health_noframe_16px.png</image_path>
<key>icon_hp</key>
</ui_tagged_images>
<ui_tagged_images record_uuid="{c09ddc5d-a45f-4bce-9300-5816d2151d95}" record_timestamp="1446125006995" record_key="icon_income">
<image_path>ui/skins/default/icon_income_plus.png</image_path>
<key>icon_income</key>
</ui_tagged_images>
<ui_tagged_images record_uuid="{23d11aeb-ee6f-4063-a30e-a5b8a07a76dc}" record_timestamp="1447673638733" record_key="icon_income_chs">
<image_path>ui/skins/wh_main_chs_chaos/icon_income_plus.png</image_path>
<key>icon_income_chs</key>
</ui_tagged_images>
<ui_tagged_images record_uuid="{e3be1d22-1e4b-4aca-88b2-dd1ee1809b35}" record_timestamp="1447673638788" record_key="icon_income_vmp">
<image_path>ui/skins/wh_main_vmp_vampire_counts/icon_income_plus.png</image_path>
<key>icon_income_vmp</key>
</ui_tagged_images>
<ui_tagged_images record_uuid="{d8080e92-038b-4747-af30-1606c43f41c3}" record_timestamp="1452078504066" record_key="icon_march_stance">
<image_path>ui/skins/default/icon_stance_march.png</image_path>
<key>icon_march_stance</key>
</ui_tagged_images>
<ui_tagged_images record_uuid="{d96fa697-cecb-4f79-bf29-0b5a3f0ba4dc}" record_timestamp="1464176218325" record_key="icon_melee_attack">
<image_path>ui/skins/default/icon_stat_attack.png</image_path>
<key>icon_melee_attack</key>
</ui_tagged_images>
<ui_tagged_images record_uuid="{63e2c53d-0bc2-4e0f-9b1c-850779b76a4d}" record_timestamp="1469455331303" record_key="icon_melee_damage">
<image_path>ui/skins/default/icon_stat_damage.png</image_path>
<key>icon_melee_damage</key>
</ui_tagged_images>
<ui_tagged_images record_uuid="{18eccf91-8e50-4b77-8b09-f1bcb8d865d0}" record_timestamp="1464176218325" record_key="icon_melee_defence">
<image_path>ui/skins/default/icon_stat_defence.png</image_path>
<key>icon_melee_defence</key>
</ui_tagged_images>
<ui_tagged_images record_uuid="{11754357-72f0-45fd-9f67-2f022250c65a}" record_timestamp="1462358725705" record_key="icon_military_access">
<image_path>ui/skins/default/treaty_military_access.png</image_path>
<key>icon_military_access</key>
</ui_tagged_images>
<ui_tagged_images record_uuid="{9e50caa5-3cfa-4e76-b636-15edc1493678}" record_timestamp="1462358725704" record_key="icon_military_alliance">
<image_path>ui/skins/default/treaty_military_alliance.png</image_path>
<key>icon_military_alliance</key>
</ui_tagged_images>
<ui_tagged_images record_uuid="{ed9f633d-57bf-4a63-a7d7-5ff1cf0557b5}" record_timestamp="1446127815608" record_key="icon_money">
<image_path>ui/skins/default/icon_income.png</image_path>
<key>icon_money</key>
</ui_tagged_images>
<ui_tagged_images record_uuid="{c3fd200e-fb58-414c-b3ad-712cc2b0645b}" record_timestamp="1447840833309" record_key="icon_money_chs">
<image_path>ui/skins/wh_main_chs_chaos/icon_income.png</image_path>
<key>icon_money_chs</key>
</ui_tagged_images>
<ui_tagged_images record_uuid="{c62e7821-e578-4f2a-b1f6-4daf56862c04}" record_timestamp="1447840833302" record_key="icon_money_vmp">
<image_path>ui/skins/wh_main_vmp_vampire_counts/icon_income.png</image_path>
<key>icon_money_vmp</key>
</ui_tagged_images>
<ui_tagged_images record_uuid="{019af63f-eb9e-4e88-b4cf-5ed78067f162}" record_timestamp="1445510306341" record_key="icon_morale">
<image_path>ui/skins/default/icon_stat_morale.png</image_path>
<key>icon_morale</key>
</ui_tagged_images>
<ui_tagged_images record_uuid="{3ebe80c0-a65a-433a-9b04-c05b947a6382}" record_timestamp="1462358725704" record_key="icon_non-aggression_pact">
<image_path>ui/skins/default/treaty_non_aggression_pact.png</image_path>
<key>icon_non-aggression_pact</key>
</ui_tagged_images>
<ui_tagged_images record_uuid="{102cc5c6-6a5a-4ca1-af16-5aae1276a753}" record_timestamp="1442573637820" record_key="icon_overseer">
<image_path>ui/skins/default/icon_governor.png</image_path>
<key>icon_overseer</key>
</ui_tagged_images>
<ui_tagged_images record_uuid="{47630969-68c2-4802-b354-09f859bea8bb}" record_timestamp="1447077593495" record_key="icon_pop_surplus">
<image_path>ui/skins/default/icon_pop_surplus.png</image_path>
<key>icon_pop_surplus</key>
</ui_tagged_images>
<ui_tagged_images record_uuid="{d70ee644-fed1-4960-b70d-f3ea3e31c295}" record_timestamp="1443088696120" record_key="icon_protagonist">
<image_path>ui/skins/default/icon_politician.png</image_path>
<key>icon_protagonist</key>
</ui_tagged_images>
<ui_tagged_images record_uuid="{e40f22cd-5db7-4b06-a70d-8029cba657e4}" record_timestamp="1442399343163" record_key="icon_public_order">
<image_path>ui/skins/default/icon_public_order_neutral.png</image_path>
<key>icon_public_order</key>
</ui_tagged_images>
<ui_tagged_images record_uuid="{dd0fc6d0-dbec-4420-b85b-23f4bd36d22f}" record_timestamp="1454334447657" record_key="icon_raiding_stance">
<image_path>ui/skins/default/icon_stance_raiding.png</image_path>
<key>icon_raiding_stance</key>
</ui_tagged_images>
<ui_tagged_images record_uuid="{116c9e37-ffb9-4972-967a-dd4197a32a2b}" record_timestamp="1464176218326" record_key="icon_range">
<image_path>ui/skins/default/icon_stat_range.png</image_path>
<key>icon_range</key>
</ui_tagged_images>
<ui_tagged_images record_uuid="{0c2eca29-fc61-4dff-ab5d-eaab06242821}" record_timestamp="1471865779688" record_key="icon_replenishment">
<image_path>ui/skins/default/icon_replenish.png</image_path>
<key>icon_replenishment</key>
</ui_tagged_images>
<ui_tagged_images record_uuid="{d7719bf1-a383-4ede-9d2a-adf1ecfe240a}" record_timestamp="1437122401627" record_key="icon_reputation">
<image_path>ui/skins/default/icon_reputation_normal.png</image_path>
<key>icon_reputation</key>
</ui_tagged_images>
<ui_tagged_images record_uuid="{76575ed5-07a6-44a8-b158-d3a9975c0234}" record_timestamp="1481892538401" record_key="icon_resistance_all">
<image_path>ui/Battle UI/ability_icons/resistance_ward_save.png</image_path>
<key>icon_resistance_all</key>
</ui_tagged_images>
<ui_tagged_images record_uuid="{1491178e-a7ab-47b0-8450-0a59c5a66af8}" record_timestamp="1481892538401" record_key="icon_resistance_fire">
<image_path>ui/Battle UI/ability_icons/resistance_fire.png</image_path>
<key>icon_resistance_fire</key>
</ui_tagged_images>
<ui_tagged_images record_uuid="{2ca456d4-3976-4d44-ac88-df1649699775}" record_timestamp="1481892538401" record_key="icon_resistance_magic">
<image_path>ui/Battle UI/ability_icons/resistance_magic.png</image_path>
<key>icon_resistance_magic</key>
</ui_tagged_images>
<ui_tagged_images record_uuid="{b9e30e6d-2456-4456-ab12-81c1b121ec42}" record_timestamp="1481892538400" record_key="icon_resistance_missile">
<image_path>ui/Battle UI/ability_icons/resistance_missile.png</image_path>
<key>icon_resistance_missile</key>
</ui_tagged_images>
<ui_tagged_images record_uuid="{57e43815-a412-4be8-8899-3e848471f9e3}" record_timestamp="1481892538400" record_key="icon_resistance_physical">
<image_path>ui/Battle UI/ability_icons/resistance_physical.png</image_path>
<key>icon_resistance_physical</key>
</ui_tagged_images>
<ui_tagged_images record_uuid="{69d948e4-68e9-483b-b286-01c4eb396f53}" record_timestamp="1464176218324" record_key="icon_shield">
<image_path>ui/skins/default/modifier_icon_shield.png</image_path>
<key>icon_shield</key>
</ui_tagged_images>
<ui_tagged_images record_uuid="{0b4f96b0-0653-4296-8743-6c6cf10567c8}" record_timestamp="1468499471623" record_key="icon_speed">
<image_path>ui/skins/default/icon_stat_speed.png</image_path>
<key>icon_speed</key>
</ui_tagged_images>
<ui_tagged_images record_uuid="{1d139737-00c9-4cde-bfb5-84eeac3801a0}" record_timestamp="1462358725703" record_key="icon_trade_agreement">
<image_path>ui/skins/default/treaty_trade_agreement.png</image_path>
<key>icon_trade_agreement</key>
</ui_tagged_images>
<ui_tagged_images record_uuid="{65fc64a1-9d62-4fdf-93d7-01d665d5c2ab}" record_timestamp="1447673638107" record_key="icon_treasury">
<image_path>ui/skins/default/icon_treasury.png</image_path>
<key>icon_treasury</key>
</ui_tagged_images>
<ui_tagged_images record_uuid="{81558535-aa45-4bf6-9892-d671986bdfa5}" record_timestamp="1447673638813" record_key="icon_treasury_chs">
<image_path>ui/skins/wh_main_chs_chaos/icon_treasury.png</image_path>
<key>icon_treasury_chs</key>
</ui_tagged_images>
<ui_tagged_images record_uuid="{14b0ade3-7473-400e-bab1-9b853a9afa1e}" record_timestamp="1447673638763" record_key="icon_treasury_vmp">
<image_path>ui/skins/wh_main_vmp_vampire_counts/icon_treasury.png</image_path>
<key>icon_treasury_vmp</key>
</ui_tagged_images>
<ui_tagged_images record_uuid="{ef3405d1-9546-4add-bbac-226265a337fe}" record_timestamp="1454334447706" record_key="icon_tunnelling_stance">
<image_path>ui/skins/default/icon_stance_use_underway.png</image_path>
<key>icon_tunnelling_stance</key>
</ui_tagged_images>
<ui_tagged_images record_uuid="{bb814791-9d9a-4e74-8862-b387eb3ebe11}" record_timestamp="1462358725710" record_key="icon_vassal">
<image_path>ui/skins/default/treaty_vassal.png</image_path>
<key>icon_vassal</key>
</ui_tagged_images>
<ui_tagged_images record_uuid="{20f6c0ee-63fc-40b8-9619-bd7c4c03b889}" record_timestamp="1460469404364" record_key="icon_wom_power">
<image_path>ui/skins/default/icon_magic_pool.png</image_path>
<key>icon_wom_power</key>
</ui_tagged_images>
<ui_tagged_images record_uuid="{9a521f6b-eaa4-4ec0-b77c-125bec68bd17}" record_timestamp="1463569484724" record_key="icon_wom_recharge">
<image_path>ui/skins/default/icon_magic_replenish_rate.png</image_path>
<key>icon_wom_recharge</key>
</ui_tagged_images>
<ui_tagged_images record_uuid="{dc66bd52-69b6-4b8a-b199-205d4c318a16}" record_timestamp="1445860057410" record_key="prelude_settlements">
<image_path>UI/Campaign UI/Effect_bundles/fortification.png</image_path>
<key>prelude_settlements</key>
</ui_tagged_images>
<ui_tagged_images record_uuid="{e7257231-aab9-4fb8-a740-d7f78e66cbbf}" record_timestamp="1442400252105" record_key="test">
<image_path>ui/skins/default/icon_stat_ammo.png</image_path>
<key>test</key>
</ui_tagged_images>
</dataroot>
